Workbook
Name _03_33_C5_C6: #REF!
Name _03_33_C5_C6: #REF!
Name _03_33_C5_C6: #REF!
Name _41_42_43_44: #REF!
Name _41_42_43_44: #REF!
Name _41_42_43_44: #REF!
Name _ASP2: [1]dis02!$AW$4
Name _ASP2: [2]dis02!$AW$4
Name _dec06: [3]globals!$C$15
Name _jun06: [3]globals!$C$9
Name _sep06: [3]globals!$C$12
Name A: #REF!
Name A: #REF!
Name A: #REF!
Name A: #REF!
Name AB: #REF!
Name AB: #REF!
Name ac: #REF!
Name ac: #REF!
Name accpd: [3]newavbsum!$AZ$9:$BI$9
Name actshortpd: [3]newavbsum!$BL$4:$BT$4
Name ADD: [4]Globals!$D$9:$D$9
Name ASP: [1]dis02!$AW$3
Name ASP: [2]dis02!$AW$3
Name B: #REF!
Name B: #REF!
Name B: #REF!
Name B: #REF!
Name b4start: #REF!
Name b4start: #REF!
Name b4start: #REF!
Name Bacs: '[1]CWL 2005'!$BC$453
Name Bacs: '[2]CWL 2005'!$BC$453
Name BBDEC95TOTAL: #REF!
Name BBDEC95TOTAL: #REF!
Name BBDEC95TOTAL: #REF!
Name BLAX_VAT: #REF!
Name BLAX_VAT: #REF!
Name BLAX_VAT: #REF!
Name bonusni: #REF!
Name bonusni: #REF!
Name budshortpd: [3]newavbsum!$T$4:$AB$4
Name CABOTPLACERT2_VAT: #REF!
Name CABOTPLACERT2_VAT: #REF!
Name CABOTPLACERT2_VAT: #REF!
Name CANADAPLACE_VAT: #REF!
Name CANADAPLACE_VAT: #REF!
Name CANADAPLACE_VAT: #REF!
Name CANCEL: #REF!
Name CANCEL: #REF!
Name CANCEL: #REF!
Name CASP: [1]dis02!$AW$2
Name CASP: [2]dis02!$AW$2
Name CoName: [5]Front!$B$4:$B$305
Name CoNo: [5]Front!$A$4:$A$305
Name CPL_VAT: #REF!
Name CPL_VAT: #REF!
Name CPL_VAT: #REF!
Name CPRUNITTRUST_VAT: #REF!
Name CPRUNITTRUST_VAT: #REF!

Sheet Instructions
B2: Please fill in the tab 'FinCharges'
B4: Please note:
A5: 1 | B5: All Yellow headed columns on Fincharges to be populated
A6: 2 | B6: The Request Reference is a name chosen for your records with a maximum of 24 characters (eg. your initials and a sequential number (SL 001), department, intial and sequential number (Tax SN 001), subject matter etc…)
A7: 3 | B7: Post Month & GL account need to be populated
A8: 4 | B8: If Recoverability and/or Budget options pop up, you need to pick one option only & populate the cell
A9: 5 | B9: VAT Rate is to be selected from a drop down menu
A10: 6 | B10: Payment Method must be selected froma drop dwon menu - Cheque for IC Offset or EFT for Cash settlement (Yardi default bank accounts associated with owners will be used)
A11: 7 | B11: Coding for Payables - input format should be GLAccount.Recoverability.Schedule - if GL account only provided GEN wil be applied by Yardi automatically
A12: 8 | B12: Add backup and approvals worksheets
A13: 9 | B13: If uploading FinCharges yourself make sure to delete content of all unused rows
B16: Link to useful information:
B18: Yardi - Useful Documents - All Documents

Sheet Instruction
B2: Weekly update guide
B4: Step 1: Membership Invoices
C5: 1.Clear current data from row 5 onwards
C6: 2.Copy from row 5 onwards, make sure it's unmerged before you paste the data
B8: Step 2: Power Query table tab
C9: 1.Right-click then click refresh
C10: 2. delete all the total columns
B12: Step 3: Upload tab
C13: 1.drag the formulas down | I13: Upload tab
C14: 2.sense check to make sure all values come back as True | H14: >>>
B16: Step 4: ETL
C17: 1.Drag all the formulas down, if needed
I20: Membership tab

Sheet ETL
A1: Fincharges | B1: Property | D1: Charge to | E1: Charge Code | F1: Net Amt | G1: Date | H1: Post Month | I1: Account | J1: AR Account | K1: Line Notes | M1: Reference | P1: Recoverability | Q1: Schedule | R1: Owner (Landlord) | S1: Business Segment | T1: Person | U1: Intercompany | Y1: Budget | AB1: Net Amount | AC1: Currency | AH1: Vat Amt | AJ1: From Date | AK1: To Date | AM1: Tran Type | AN1: Tax Rate | AP1: Payment Method | AQ1: Coding for Payables | AS1: Job | AT1: Category | AU1: Costcode | AV1: Contract | BE1: Display Type
A2: TRANNUM | B2: PROPERTY | C2: REF_PROPERTY_ID | D2: PERSON | E2: OFFSET | F2: AMOUNT | G2: DATE | H2: POSTMONTH | I2: ACCOUNT | J2: ACCRUAL | K2: NOTES | L2: USERDEFINEDFIELD1 | M2: REF | N2: DOCUMENTSEQUENCENUMBER | O2: UNIT | P2: SEGMENT1 | Q2: SEGMENT2 | R2: SEGMENT3 | S2: SEGMENT4 | T2: SEGMENT5 | U2: SEGMENT6 | V2: SEGMENT7 | W2: SEGMENT8 | X2: SEGMENT9 | Y2: SEGMENT10 | Z2: SEGMENT11 | AA2: SEGMENT12 | AB2: TRANAMOUNT | AC2: TRANCURRENCYID | AD2: EXCHANGERATE | AE2: EXCHANGERATEDATE | AF2: EXCHANGERATE2 | AG2: EXCHANGERATEDATE2 | AH2: TAXAMOUNT1 | AI2: TAXAMOUNT2 | AJ2: FROMDATE | AK2: TODATE | AL2: TAXPOINTDATE | AM2: VATTRANTYPEID | AN2: VATRATEID | AO2: TRANDATE | AP2: INTERNATIONALPAYMENTTYPE | AQ2: NOTES2 | AR2: FUNCTIONALCURRENCYAMOUNT | AS2: JOB | AT2: CATEGORY | AU2: CostCode | AV2: Contract | AW2: TRANFIELD1 | AX2: TRANFIELD2 | AY2: TRANFIELD3 | AZ2: TRANFIELD4 | BA2: TRANFIELD5 | BB2: TRANFIELD6 | BC2: TRANFIELD7 | BD2: TRANFIELD8 | BE2: DISPLAYTYPE
A3: 1 | B3: c0et | D3: ='Upload tab'!A3 -> c0000935 | E3: misc | F3: ='Upload tab'!B3 -> 440 | G3: =TODAY() -> 46070 | H3: =G3 -> 46070 | I3: =SUBSTITUTE('Upload tab'!E3,"-","") -> 42113011 | J3: 12212311 | K3: ='Upload tab'!F3 -> L3924638-JEB ENGINEERING SERVICES LLP | N3: 1 | P3: GEN | Y3: Lvl39 | AB3: =F3 -> 440 | AC3: gbp | AH3: =IF(AN3="UKSTD20",F3*0.2,(IF(AN3="UKred5",F3*0.05,0))) -> 0 | AJ3: ='Upload tab'!H3 -> 01/02/2025 | AK3: ='Upload tab'!I3 -> 28/02/2026 | AM3: =_xlfn.IFNA(_xlfn.XLOOKUP(AN3,VAT!$A$1:$A$10,VAT!$D$1:$D$10),"") | AN3: {=_xlfn.IFNA(_xlfn.IFS(LEFT(M3,4)="L39N","outside",LEFT(M3,3)="L39","ukstd20"),"")} | AO3: 45869 | AP3: EFT | BE3: STANDARD CHARGE DISPLAY TYPE | CB3: 0 | CC3: 0 | CD3: 0
AN4: {=_xlfn.IFNA(_xlfn.IFS(LEFT(M4,4)="L39N","outside",LEFT(M4,3)="L39","ukstd20"),"")}
AN6: {=_xlfn.IFNA(_xlfn.IFS(LEFT(M6,4)="L39N","outside",LEFT(M6,3)="L39","ukstd20"),"")}
AN7: {=_xlfn.IFNA(_xlfn.IFS(LEFT(M7,4)="L39N","outside",LEFT(M7,3)="L39","ukstd20"),"")}
AN8: {=_xlfn.IFNA(_xlfn.IFS(LEFT(M8,4)="L39N","outside",LEFT(M8,3)="L39","ukstd20"),"")}
AN9: {=_xlfn.IFNA(_xlfn.IFS(LEFT(M9,4)="L39N","outside",LEFT(M9,3)="L39","ukstd20"),"")}
AN10: {=_xlfn.IFNA(_xlfn.IFS(LEFT(M10,4)="L39N","outside",LEFT(M10,3)="L39","ukstd20"),"")}
AN11: {=_xlfn.IFNA(_xlfn.IFS(LEFT(M11,4)="L39N","outside",LEFT(M11,3)="L39","ukstd20"),"")}
AN12: {=_xlfn.IFNA(_xlfn.IFS(LEFT(M12,4)="L39N","outside",LEFT(M12,3)="L39","ukstd20"),"")}
AN13: {=_xlfn.IFNA(_xlfn.IFS(LEFT(M13,4)="L39N","outside",LEFT(M13,3)="L39","ukstd20"),"")}
AN14: {=_xlfn.IFNA(_xlfn.IFS(LEFT(M14,4)="L39N","outside",LEFT(M14,3)="L39","ukstd20"),"")}
AN15: {=_xlfn.IFNA(_xlfn.IFS(LEFT(M15,4)="L39N","outside",LEFT(M15,3)="L39","ukstd20"),"")}
AN16: {=_xlfn.IFNA(_xlfn.IFS(LEFT(M16,4)="L39N","outside",LEFT(M16,3)="L39","ukstd20"),"")}
... AN221: {=_xlfn.IFNA(_xlfn.IFS(LEFT(M221,4)="L39N","outside",LEFT(M221,3)="L39","ukstd20"),"")}

Sheet Upload tab
A1: Charge to | B1: Net Amt | C1: Date | D1: Post Month | E1: Account | F1: Line Notes | G1: Reference | H1: From Date | I1: To Date
A2: PERSON | B2: AMOUNT | C2: DATE | D2: POSTMONTH | E2: ACCOUNT | F2: NOTES | G2: REF | H2: FROMDATE | I2: TODATE | K2: Nominal Code | L2: Upload tab | N2: ETL
A3: =IF(LEFT(F3,4)="L39N","c0001836",IF(LEFT(F3,3)="L24","c0000008",IF(LEFT(F3,3)="L39","c0000935",""))) -> c0000935 | B3: ='Power Query Table'!P2 -> 440 | C3: =TODAY() -> 46070 | D3: =TODAY() -> 46070 | E3: =LEFT('Power Query Table'!O2,9) -> 4211-3011 | F3: =CONCATENATE('Power Query Table'!A2, "-","",'Power Query Table'!B2) -> L3924638-JEB ENGINEERING SERVICES LLP | G3: =IF(LEFT(F3,4)="L39N",LEFT(F3,9),LEFT(F3,8)) -> L3924638 | H3: =TEXT(DATE(2025,MONTH(TODAY()),1),"dd/mm/yyyy") -> 01/02/2025 | I3: =TEXT(EOMONTH(TODAY(),0),"dd/mm/yyyy") -> 28/02/2026 | K3: {=_xlfn.UNIQUE(E:E,FALSE,FALSE)} -> Account
A4: =IF(LEFT(F4,4)="L39N","c0001836",IF(LEFT(F4,3)="L24","c0000008",IF(LEFT(F4,3)="L39","c0000935",""))) -> #REF! | B4: ='Power Query Table'!#REF! -> #REF! | C4: =TODAY() -> 46070 | D4: =TODAY() -> 46070 | E4: =LEFT('Power Query Table'!#REF!,9) -> #REF! | F4: =CONCATENATE('Power Query Table'!#REF!, "-","",'Power Query Table'!#REF!) -> #REF! | G4: =IF(LEFT(F4,4)="L39N",LEFT(F4,9),LEFT(F4,8)) -> #REF! | H4: =TEXT(DATE(2025,MONTH(TODAY()),1),"dd/mm/yyyy") -> 01/02/2025 | I4: =TEXT(EOMONTH(TODAY(),0),"dd/mm/yyyy") -> 28/02/2026 | K4: ACCOUNT
A5: =IF(LEFT(F5,4)="L39N","c0001836",IF(LEFT(F5,3)="L24","c0000008",IF(LEFT(F5,3)="L39","c0000935",""))) -> #REF! | B5: ='Power Query Table'!#REF! -> #REF! | C5: =TODAY() -> 46070 | D5: =TODAY() -> 46070 | E5: =LEFT('Power Query Table'!#REF!,9) -> #REF! | F5: =CONCATENATE('Power Query Table'!#REF!, "-","",'Power Query Table'!#REF!) -> #REF! | G5: =IF(LEFT(F5,4)="L39N",LEFT(F5,9),LEFT(F5,8)) -> #REF! | H5: =TEXT(DATE(2025,MONTH(TODAY()),1),"dd/mm/yyyy") -> 01/02/2025 | I5: =TEXT(EOMONTH(TODAY(),0),"dd/mm/yyyy") -> 28/02/2026 | K5: 4211-3011 | L5: =SUMIFS(B:B,E:E,K5) -> 440 | M5: =SUBSTITUTE(K5,"-","") -> 42113011 | N5: =SUMIFS(ETL!F:F,ETL!I:I,'Upload tab'!M5) -> 440 | O5: =L5=N5 -> TRUE
A6: =IF(LEFT(F6,4)="L39N","c0001836",IF(LEFT(F6,3)="L24","c0000008",IF(LEFT(F6,3)="L39","c0000935",""))) -> #REF! | B6: ='Power Query Table'!#REF! -> #REF! | C6: =TODAY() -> 46070 | D6: =TODAY() -> 46070 | E6: =LEFT('Power Query Table'!#REF!,9) -> #REF! | F6: =CONCATENATE('Power Query Table'!#REF!, "-","",'Power Query Table'!#REF!) -> #REF! | G6: =IF(LEFT(F6,4)="L39N",LEFT(F6,9),LEFT(F6,8)) -> #REF! | H6: =TEXT(DATE(2025,MONTH(TODAY()),1),"dd/mm/yyyy") -> 01/02/2025 | I6: =TEXT(EOMONTH(TODAY(),0),"dd/mm/yyyy") -> 28/02/2026 | K6: #REF! | L6: =SUMIFS(B:B,E:E,K6) -> #REF! | M6: =SUBSTITUTE(K6,"-","") -> #REF! | N6: =SUMIFS(ETL!F:F,ETL!I:I,'Upload tab'!M6) -> 0 | O6: =L6=N6 -> #REF!
A7: =IF(LEFT(F7,4)="L39N","c0001836",IF(LEFT(F7,3)="L24","c0000008",IF(LEFT(F7,3)="L39","c0000935",""))) -> #REF! | B7: ='Power Query Table'!#REF! -> #REF! | C7: =TODAY() -> 46070 | D7: =TODAY() -> 46070 | E7: =LEFT('Power Query Table'!#REF!,9) -> #REF! | F7: =CONCATENATE('Power Query Table'!#REF!, "-","",'Power Query Table'!#REF!) -> #REF! | G7: =IF(LEFT(F7,4)="L39N",LEFT(F7,9),LEFT(F7,8)) -> #REF! | H7: =TEXT(DATE(2025,MONTH(TODAY()),1),"dd/mm/yyyy") -> 01/02/2025 | I7: =TEXT(EOMONTH(TODAY(),0),"dd/mm/yyyy") -> 28/02/2026 | K7: 0 | L7: =SUMIFS(B:B,E:E,K7) -> 0 | M7: =SUBSTITUTE(K7,"-","") -> 0 | N7: =SUMIFS(ETL!F:F,ETL!I:I,'Upload tab'!M7) -> 0 | O7: =L7=N7 -> TRUE
A8: =IF(LEFT(F8,4)="L39N","c0001836",IF(LEFT(F8,3)="L24","c0000008",IF(LEFT(F8,3)="L39","c0000935",""))) -> #REF! | B8: ='Power Query Table'!#REF! -> #REF! | C8: =TODAY() -> 46070 | D8: =TODAY() -> 46070 | E8: =LEFT('Power Query Table'!#REF!,9) -> #REF! | F8: =CONCATENATE('Power Query Table'!#REF!, "-","",'Power Query Table'!#REF!) -> #REF! | G8: =IF(LEFT(F8,4)="L39N",LEFT(F8,9),LEFT(F8,8)) -> #REF! | H8: =TEXT(DATE(2025,MONTH(TODAY()),1),"dd/mm/yyyy") -> 01/02/2025 | I8: =TEXT(EOMONTH(TODAY(),0),"dd/mm/yyyy") -> 28/02/2026 | L8: =SUMIFS(B:B,E:E,K8) -> 0 | M8: =SUBSTITUTE(K8,"-","") | N8: =SUMIFS(ETL!F:F,ETL!I:I,'Upload tab'!M8) -> 0 | O8: =L8=N8 -> TRUE
A9: =IF(LEFT(F9,4)="L39N","c0001836",IF(LEFT(F9,3)="L24","c0000008",IF(LEFT(F9,3)="L39","c0000935",""))) -> #REF! | B9: ='Power Query Table'!#REF! -> #REF! | C9: =TODAY() -> 46070 | D9: =TODAY() -> 46070 | E9: =LEFT('Power Query Table'!#REF!,9) -> #REF! | F9: =CONCATENATE('Power Query Table'!#REF!, "-","",'Power Query Table'!#REF!) -> #REF! | G9: =IF(LEFT(F9,4)="L39N",LEFT(F9,9),LEFT(F9,8)) -> #REF! | H9: =TEXT(DATE(2025,MONTH(TODAY()),1),"dd/mm/yyyy") -> 01/02/2025 | I9: =TEXT(EOMONTH(TODAY(),0),"dd/mm/yyyy") -> 28/02/2026 | L9: =SUMIFS(B:B,E:E,K9) -> 0 | M9: =SUBSTITUTE(K9,"-","") | N9: =SUMIFS(ETL!F:F,ETL!I:I,'Upload tab'!M9) -> 0 | O9: =L9=N9 -> TRUE
A10: =IF(LEFT(F10,4)="L39N","c0001836",IF(LEFT(F10,3)="L24","c0000008",IF(LEFT(F10,3)="L39","c0000935",""))) -> #REF! | B10: ='Power Query Table'!#REF! -> #REF! | C10: =TODAY() -> 46070 | D10: =TODAY() -> 46070 | E10: =LEFT('Power Query Table'!#REF!,9) -> #REF! | F10: =CONCATENATE('Power Query Table'!#REF!, "-","",'Power Query Table'!#REF!) -> #REF! | G10: =IF(LEFT(F10,4)="L39N",LEFT(F10,9),LEFT(F10,8)) -> #REF! | H10: =TEXT(DATE(2025,MONTH(TODAY()),1),"dd/mm/yyyy") -> 01/02/2025 | I10: =TEXT(EOMONTH(TODAY(),0),"dd/mm/yyyy") -> 28/02/2026 | L10: =SUMIFS(B:B,E:E,K10) -> 0 | M10: =SUBSTITUTE(K10,"-","") | N10: =SUMIFS(ETL!F:F,ETL!I:I,'Upload tab'!M10) -> 0 | O10: =L10=N10 -> TRUE
A11: =IF(LEFT(F11,4)="L39N","c0001836",IF(LEFT(F11,3)="L24","c0000008",IF(LEFT(F11,3)="L39","c0000935",""))) -> #REF! | B11: ='Power Query Table'!#REF! -> #REF! | C11: =TODAY() -> 46070 | D11: =TODAY() -> 46070 | E11: =LEFT('Power Query Table'!#REF!,9) -> #REF! | F11: =CONCATENATE('Power Query Table'!#REF!, "-","",'Power Query Table'!#REF!) -> #REF! | G11: =IF(LEFT(F11,4)="L39N",LEFT(F11,9),LEFT(F11,8)) -> #REF! | H11: =TEXT(DATE(2025,MONTH(TODAY()),1),"dd/mm/yyyy") -> 01/02/2025 | I11: =TEXT(EOMONTH(TODAY(),0),"dd/mm/yyyy") -> 28/02/2026 | L11: =SUMIFS(B:B,E:E,K11) -> 0 | M11: =SUBSTITUTE(K11,"-","") | N11: =SUMIFS(ETL!F:F,ETL!I:I,'Upload tab'!M11) -> 0 | O11: =L11=N11 -> TRUE
A12: =IF(LEFT(F12,4)="L39N","c0001836",IF(LEFT(F12,3)="L24","c0000008",IF(LEFT(F12,3)="L39","c0000935",""))) -> #REF! | B12: ='Power Query Table'!#REF! -> #REF! | C12: =TODAY() -> 46070 | D12: =TODAY() -> 46070 | E12: =LEFT('Power Query Table'!#REF!,9) -> #REF! | F12: =CONCATENATE('Power Query Table'!#REF!, "-","",'Power Query Table'!#REF!) -> #REF! | G12: =IF(LEFT(F12,4)="L39N",LEFT(F12,9),LEFT(F12,8)) -> #REF! | H12: =TEXT(DATE(2025,MONTH(TODAY()),1),"dd/mm/yyyy") -> 01/02/2025 | I12: =TEXT(EOMONTH(TODAY(),0),"dd/mm/yyyy") -> 28/02/2026 | L12: =SUMIFS(B:B,E:E,K12) -> 0 | M12: =SUBSTITUTE(K12,"-","") | N12: =SUMIFS(ETL!F:F,ETL!I:I,'Upload tab'!M12) -> 0 | O12: =L12=N12 -> TRUE
A13: =IF(LEFT(F13,4)="L39N","c0001836",IF(LEFT(F13,3)="L24","c0000008",IF(LEFT(F13,3)="L39","c0000935",""))) -> #REF! | B13: ='Power Query Table'!#REF! -> #REF! | C13: =TODAY() -> 46070 | D13: =TODAY() -> 46070 | E13: =LEFT('Power Query Table'!#REF!,9) -> #REF! | F13: =CONCATENATE('Power Query Table'!#REF!, "-","",'Power Query Table'!#REF!) -> #REF! | G13: =IF(LEFT(F13,4)="L39N",LEFT(F13,9),LEFT(F13,8)) -> #REF! | H13: =TEXT(DATE(2025,MONTH(TODAY()),1),"dd/mm/yyyy") -> 01/02/2025 | I13: =TEXT(EOMONTH(TODAY(),0),"dd/mm/yyyy") -> 28/02/2026 | L13: =SUMIFS(B:B,E:E,K13) -> 0 | M13: =SUBSTITUTE(K13,"-","") | N13: =SUMIFS(ETL!F:F,ETL!I:I,'Upload tab'!M13) -> 0 | O13: =L13=N13 -> TRUE
A14: =IF(LEFT(F14,4)="L39N","c0001836",IF(LEFT(F14,3)="L24","c0000008",IF(LEFT(F14,3)="L39","c0000935",""))) -> #REF! | B14: ='Power Query Table'!#REF! -> #REF! | C14: =TODAY() -> 46070 | D14: =TODAY() -> 46070 | E14: =LEFT('Power Query Table'!#REF!,9) -> #REF! | F14: =CONCATENATE('Power Query Table'!#REF!, "-","",'Power Query Table'!#REF!) -> #REF! | G14: =IF(LEFT(F14,4)="L39N",LEFT(F14,9),LEFT(F14,8)) -> #REF! | H14: =TEXT(DATE(2025,MONTH(TODAY()),1),"dd/mm/yyyy") -> 01/02/2025 | I14: =TEXT(EOMONTH(TODAY(),0),"dd/mm/yyyy") -> 28/02/2026 | L14: =SUMIFS(B:B,E:E,K14) -> 0 | M14: =SUBSTITUTE(K14,"-","") | N14: =SUMIFS(ETL!F:F,ETL!I:I,'Upload tab'!M14) -> 0 | O14: =L14=N14 -> TRUE
A15: =IF(LEFT(F15,4)="L39N","c0001836",IF(LEFT(F15,3)="L24","c0000008",IF(LEFT(F15,3)="L39","c0000935",""))) -> #REF! | B15: ='Power Query Table'!#REF! -> #REF! | C15: =TODAY() -> 46070 | D15: =TODAY() -> 46070 | E15: =LEFT('Power Query Table'!#REF!,9) -> #REF! | F15: =CONCATENATE('Power Query Table'!#REF!, "-","",'Power Query Table'!#REF!) -> #REF! | G15: =IF(LEFT(F15,4)="L39N",LEFT(F15,9),LEFT(F15,8)) -> #REF! | H15: =TEXT(DATE(2025,MONTH(TODAY()),1),"dd/mm/yyyy") -> 01/02/2025 | I15: =TEXT(EOMONTH(TODAY(),0),"dd/mm/yyyy") -> 28/02/2026 | L15: =SUMIFS(B:B,E:E,K15) -> 0 | M15: =SUBSTITUTE(K15,"-","") | N15: =SUMIFS(ETL!F:F,ETL!I:I,'Upload tab'!M15) -> 0 | O15: =L15=N15 -> TRUE
A16: =IF(LEFT(F16,4)="L39N","c0001836",IF(LEFT(F16,3)="L24","c0000008",IF(LEFT(F16,3)="L39","c0000935",""))) -> #REF! | B16: ='Power Query Table'!#REF! -> #REF! | C16: =TODAY() -> 46070 | D16: =TODAY() -> 46070 | E16: =LEFT('Power Query Table'!#REF!,9) -> #REF! | F16: =CONCATENATE('Power Query Table'!#REF!, "-","",'Power Query Table'!#REF!) -> #REF! | G16: =IF(LEFT(F16,4)="L39N",LEFT(F16,9),LEFT(F16,8)) -> #REF! | H16: =TEXT(DATE(2025,MONTH(TODAY()),1),"dd/mm/yyyy") -> 01/02/2025 | I16: =TEXT(EOMONTH(TODAY(),0),"dd/mm/yyyy") -> 28/02/2026 | L16: =SUMIFS(B:B,E:E,K16) -> 0 | M16: =SUBSTITUTE(K16,"-","") | N16: =SUMIFS(ETL!F:F,ETL!I:I,'Upload tab'!M16) -> 0 | O16: =L16=N16 -> TRUE
A17: =IF(LEFT(F17,4)="L39N","c0001836",IF(LEFT(F17,3)="L24","c0000008",IF(LEFT(F17,3)="L39","c0000935",""))) -> #REF! | B17: ='Power Query Table'!#REF! -> #REF! | C17: =TODAY() -> 46070 | D17: =TODAY() -> 46070 | E17: =LEFT('Power Query Table'!#REF!,9) -> #REF! | F17: =CONCATENATE('Power Query Table'!#REF!, "-","",'Power Query Table'!#REF!) -> #REF! | G17: =IF(LEFT(F17,4)="L39N",LEFT(F17,9),LEFT(F17,8)) -> #REF! | H17: =TEXT(DATE(2025,MONTH(TODAY()),1),"dd/mm/yyyy") -> 01/02/2025 | I17: =TEXT(EOMONTH(TODAY(),0),"dd/mm/yyyy") -> 28/02/2026 | L17: =SUMIFS(B:B,E:E,K17) -> 0 | M17: =SUBSTITUTE(K17,"-","") | N17: =SUMIFS(ETL!F:F,ETL!I:I,'Upload tab'!M17) -> 0 | O17: =L17=N17 -> TRUE
A18: =IF(LEFT(F18,4)="L39N","c0001836",IF(LEFT(F18,3)="L24","c0000008",IF(LEFT(F18,3)="L39","c0000935",""))) -> #REF! | B18: ='Power Query Table'!#REF! -> #REF! | C18: =TODAY() -> 46070 | D18: =TODAY() -> 46070 | E18: =LEFT('Power Query Table'!#REF!,9) -> #REF! | F18: =CONCATENATE('Power Query Table'!#REF!, "-","",'Power Query Table'!#REF!) -> #REF! | G18: =IF(LEFT(F18,4)="L39N",LEFT(F18,9),LEFT(F18,8)) -> #REF! | H18: =TEXT(DATE(2025,MONTH(TODAY()),1),"dd/mm/yyyy") -> 01/02/2025 | I18: =TEXT(EOMONTH(TODAY(),0),"dd/mm/yyyy") -> 28/02/2026 | L18: =SUMIFS(B:B,E:E,K18) -> 0 | M18: =SUBSTITUTE(K18,"-","") | N18: =SUMIFS(ETL!F:F,ETL!I:I,'Upload tab'!M18) -> 0 | O18: =L18=N18 -> TRUE
A19: =IF(LEFT(F19,4)="L39N","c0001836",IF(LEFT(F19,3)="L24","c0000008",IF(LEFT(F19,3)="L39","c0000935",""))) -> #REF! | B19: ='Power Query Table'!#REF! -> #REF! | C19: =TODAY() -> 46070 | D19: =TODAY() -> 46070 | E19: =LEFT('Power Query Table'!#REF!,9) -> #REF! | F19: =CONCATENATE('Power Query Table'!#REF!, "-","",'Power Query Table'!#REF!) -> #REF! | G19: =IF(LEFT(F19,4)="L39N",LEFT(F19,9),LEFT(F19,8)) -> #REF! | H19: =TEXT(DATE(2025,MONTH(TODAY()),1),"dd/mm/yyyy") -> 01/02/2025 | I19: =TEXT(EOMONTH(TODAY(),0),"dd/mm/yyyy") -> 28/02/2026 | L19: =SUMIFS(B:B,E:E,K19) -> 0 | M19: =SUBSTITUTE(K19,"-","") | N19: =SUMIFS(ETL!F:F,ETL!I:I,'Upload tab'!M19) -> 0 | O19: =L19=N19 -> TRUE
... A28: =IF(LEFT(F28,4)="L39N","c0001836",IF(LEFT(F28,3)="L24","c0000008",IF(LEFT(F28,3)="L39","c0000935",""))) -> #REF! | B28: ='Power Query Table'!#REF! -> #REF! | C28: =TODAY() -> 46070 | D28: =TODAY() -> 46070 | E28: =LEFT('Power Query Table'!#REF!,9) -> #REF! | F28: =CONCATENATE('Power Query Table'!#REF!, "-","",'Power Query Table'!#REF!) -> #REF! | G28: =IF(LEFT(F28,4)="L39N",LEFT(F28,9),LEFT(F28,8)) -> #REF! | H28: =TEXT(DATE(2025,MONTH(TODAY()),1),"dd/mm/yyyy") -> 01/02/2025 | I28: =TEXT(EOMONTH(TODAY(),0),"dd/mm/yyyy") -> 28/02/2026 | L28: =SUMIFS(B:B,E:E,K28) -> 0 | M28: =SUBSTITUTE(K28,"-","") | N28: =SUMIFS(ETL!F:F,ETL!I:I,'Upload tab'!M28) -> 0 | O28: =L28=N28 -> TRUE
A29: =IF(LEFT(F29,4)="L39N","c0001836",IF(LEFT(F29,3)="L24","c0000008",IF(LEFT(F29,3)="L39","c0000935",""))) -> #REF! | B29: ='Power Query Table'!#REF! -> #REF! | C29: =TODAY() -> 46070 | D29: =TODAY() -> 46070 | E29: =LEFT('Power Query Table'!#REF!,9) -> #REF! | F29: =CONCATENATE('Power Query Table'!#REF!, "-","",'Power Query Table'!#REF!) -> #REF! | G29: =IF(LEFT(F29,4)="L39N",LEFT(F29,9),LEFT(F29,8)) -> #REF! | H29: =TEXT(DATE(2025,MONTH(TODAY()),1),"dd/mm/yyyy") -> 01/02/2025 | I29: =TEXT(EOMONTH(TODAY(),0),"dd/mm/yyyy") -> 28/02/2026 | K29: Total | L29: =SUM(L5:L10) -> #REF! | M29: =SUBSTITUTE(K29,"-","") -> Total | N29: =SUM(N5:N10) -> 440 | O29: =L29=N29 -> #REF!
A30: =IF(LEFT(F30,4)="L39N","c0001836",IF(LEFT(F30,3)="L24","c0000008",IF(LEFT(F30,3)="L39","c0000935",""))) -> #REF! | B30: ='Power Query Table'!#REF! -> #REF! | C30: =TODAY() -> 46070 | D30: =TODAY() -> 46070 | E30: =LEFT('Power Query Table'!#REF!,9) -> #REF! | F30: =CONCATENATE('Power Query Table'!#REF!, "-","",'Power Query Table'!#REF!) -> #REF! | G30: =IF(LEFT(F30,4)="L39N",LEFT(F30,9),LEFT(F30,8)) -> #REF! | H30: =TEXT(DATE(2025,MONTH(TODAY()),1),"dd/mm/yyyy") -> 01/02/2025 | I30: =TEXT(EOMONTH(TODAY(),0),"dd/mm/yyyy") -> 28/02/2026
K33: Nominal Code | L33: Upload tab | M33: Membership
K34: {=_xlfn.UNIQUE('Power Query Table'!O:O,FALSE,FALSE)} -> Attribute
K35: 4211-3011 - L39 Hot Desk Membership (2024) | L35: =SUMIFS('Power Query Table'!P:P,'Power Query Table'!O:O,'Upload tab'!K35) -> 440 | M35: =INDEX('Membership invoices'!$7:$7,MATCH('Upload tab'!K35,'Membership invoices'!$5:$5,0)) -> #N/A | N35: =L35=M35 -> #N/A
K36: 0 | L36: =SUMIFS('Power Query Table'!P:P,'Power Query Table'!O:O,'Upload tab'!K36) -> 0 | M36: =INDEX('Membership invoices'!$32:$32,MATCH('Upload tab'!K36,'Membership invoices'!$5:$5,0)) -> #N/A | N36: =L36=M36 -> #N/A
L37: =SUMIFS('Power Query Table'!P:P,'Power Query Table'!O:O,'Upload tab'!K37) -> 0 | M37: =INDEX('Membership invoices'!$32:$32,MATCH('Upload tab'!K37,'Membership invoices'!$5:$5,0)) -> #N/A | N37: =L37=M37 -> #N/A
L38: =SUMIFS('Power Query Table'!P:P,'Power Query Table'!O:O,'Upload tab'!K38) -> 0 | M38: =INDEX('Membership invoices'!$32:$32,MATCH('Upload tab'!K38,'Membership invoices'!$5:$5,0)) -> #N/A | N38: =L38=M38 -> #N/A
L39: =SUMIFS('Power Query Table'!P:P,'Power Query Table'!O:O,'Upload tab'!K39) -> 0 | M39: =INDEX('Membership invoices'!$32:$32,MATCH('Upload tab'!K39,'Membership invoices'!$5:$5,0)) -> #N/A | N39: =L39=M39 -> #N/A
L40: =SUMIFS('Power Query Table'!P:P,'Power Query Table'!O:O,'Upload tab'!K40) -> 0 | M40: =INDEX('Membership invoices'!$32:$32,MATCH('Upload tab'!K40,'Membership invoices'!$5:$5,0)) -> #N/A | N40: =L40=M40 -> #N/A
L41: =SUMIFS('Power Query Table'!P:P,'Power Query Table'!O:O,'Upload tab'!K41) -> 0 | M41: =INDEX('Membership invoices'!$180:$180,MATCH('Upload tab'!K41,'Membership invoices'!$5:$5,0)) -> #N/A | N41: =L41=M41 -> #N/A
L42: =SUMIFS('Power Query Table'!P:P,'Power Query Table'!O:O,'Upload tab'!K42) -> 0 | M42: =INDEX('Membership invoices'!$180:$180,MATCH('Upload tab'!K42,'Membership invoices'!$5:$5,0)) -> #N/A | N42: =L42=M42 -> #N/A
L43: =SUMIFS('Power Query Table'!P:P,'Power Query Table'!O:O,'Upload tab'!K43) -> 0 | M43: =INDEX('Membership invoices'!$180:$180,MATCH('Upload tab'!K43,'Membership invoices'!$5:$5,0)) -> #N/A | N43: =L43=M43 -> #N/A
L44: =SUMIFS('Power Query Table'!P:P,'Power Query Table'!O:O,'Upload tab'!K44) -> 0 | M44: =INDEX('Membership invoices'!$180:$180,MATCH('Upload tab'!K44,'Membership invoices'!$5:$5,0)) -> #N/A | N44: =L44=M44 -> #N/A
L45: =SUMIFS('Power Query Table'!P:P,'Power Query Table'!O:O,'Upload tab'!K45) -> 0 | M45: =INDEX('Membership invoices'!$192:$192,MATCH('Upload tab'!K45,'Membership invoices'!$5:$5,0)) -> #N/A | N45: =L45=M45 -> #N/A
L46: =SUMIFS('Power Query Table'!P:P,'Power Query Table'!O:O,'Upload tab'!K46) -> 0 | M46: =INDEX('Membership invoices'!$192:$192,MATCH('Upload tab'!K46,'Membership invoices'!$5:$5,0)) -> #N/A | N46: =L46=M46 -> #N/A
L47: =SUMIFS('Power Query Table'!P:P,'Power Query Table'!O:O,'Upload tab'!K47) -> 0 | M47: =INDEX('Membership invoices'!$192:$192,MATCH('Upload tab'!K47,'Membership invoices'!$5:$5,0)) -> #N/A | N47: =L47=M47 -> #N/A
L48: =SUMIFS('Power Query Table'!P:P,'Power Query Table'!O:O,'Upload tab'!K48) -> 0 | M48: =INDEX('Membership invoices'!$192:$192,MATCH('Upload tab'!K48,'Membership invoices'!$5:$5,0)) -> #N/A | N48: =L48=M48 -> #N/A
L49: =SUMIFS('Power Query Table'!P:P,'Power Query Table'!O:O,'Upload tab'!K49) -> 0 | M49: =INDEX('Membership invoices'!$192:$192,MATCH('Upload tab'!K49,'Membership invoices'!$5:$5,0)) -> #N/A | N49: =L49=M49 -> #N/A
L50: =SUMIFS('Power Query Table'!P:P,'Power Query Table'!O:O,'Upload tab'!K50) -> 0 | M50: =INDEX('Membership invoices'!$192:$192,MATCH('Upload tab'!K50,'Membership invoices'!$5:$5,0)) -> #N/A | N50: =L50=M50 -> #N/A
L51: =SUMIFS('Power Query Table'!P:P,'Power Query Table'!O:O,'Upload tab'!K51) -> 0 | M51: =INDEX('Membership invoices'!$192:$192,MATCH('Upload tab'!K51,'Membership invoices'!$5:$5,0)) -> #N/A | N51: =L51=M51 -> #N/A
L52: =SUMIFS('Power Query Table'!P:P,'Power Query Table'!O:O,'Upload tab'!K52) -> 0 | M52: =INDEX('Membership invoices'!$192:$192,MATCH('Upload tab'!K52,'Membership invoices'!$5:$5,0)) -> #N/A | N52: =L52=M52 -> #N/A
L53: =SUMIFS('Power Query Table'!P:P,'Power Query Table'!O:O,'Upload tab'!K53) -> 0 | M53: =INDEX('Membership invoices'!$192:$192,MATCH('Upload tab'!K53,'Membership invoices'!$5:$5,0)) -> #N/A | N53: =L53=M53 -> #N/A
L54: =SUMIFS('Power Query Table'!P:P,'Power Query Table'!O:O,'Upload tab'!K54) -> 0 | M54: =INDEX('Membership invoices'!$192:$192,MATCH('Upload tab'!K54,'Membership invoices'!$5:$5,0)) -> #N/A | N54: =L54=M54 -> #N/A
L55: =SUMIFS('Power Query Table'!P:P,'Power Query Table'!O:O,'Upload tab'!K55) -> 0 | M55: =INDEX('Membership invoices'!$192:$192,MATCH('Upload tab'!K55,'Membership invoices'!$5:$5,0)) -> #N/A | N55: =L55=M55 -> #N/A
L56: =SUMIFS('Power Query Table'!P:P,'Power Query Table'!O:O,'Upload tab'!K56) -> 0 | M56: =INDEX('Membership invoices'!$192:$192,MATCH('Upload tab'!K56,'Membership invoices'!$5:$5,0)) -> #N/A | N56: =L56=M56 -> #N/A
... L59: =SUMIFS('Power Query Table'!P:P,'Power Query Table'!O:O,'Upload tab'!K59) -> 0 | M59: =INDEX('Membership invoices'!$192:$192,MATCH('Upload tab'!K59,'Membership invoices'!$5:$5,0)) -> #N/A | N59: =L59=M59 -> #N/A
K60: Total | L60: =SUM(L35:L44) -> 440 | M60: =SUM(M35:M40) -> #N/A | N60: =L60=M60 -> #N/A
A244: =IF(LEFT(F244,4)="L39N","c0001836",IF(LEFT(F244,3)="L24","c0000008",IF(LEFT(F244,3)="L39","c0000935","")))

Sheet Data Details ->>

Sheet Sheet1
A1: L3917096 | B1: =_xlfn.XLOOKUP(A1,#REF!,#REF!,"",0,1) -> #REF! | D1: L3917096 | F1: Invoice #
A2: L3917104 | B2: =_xlfn.XLOOKUP(A2,#REF!,#REF!,"",0,1) -> #REF! | D2: L3917104 | F2: L3917096
A3: L3917111 | B3: =_xlfn.XLOOKUP(A3,#REF!,#REF!,"",0,1) -> #REF! | D3: L3917111 | F3: L3917104
A4: L3917336 | B4: =_xlfn.XLOOKUP(A4,#REF!,#REF!,"",0,1) -> #REF! | D4: L3917336 | F4: L3917111
A5: L3917283 | B5: =_xlfn.XLOOKUP(A5,#REF!,#REF!,"",0,1) -> #REF! | D5: L3917283 | F5: L3917336
A6: L3917544 | B6: =_xlfn.XLOOKUP(A6,#REF!,#REF!,"",0,1) -> #REF! | D6: L3917544 | F6: L3917283
A7: L3917618 | B7: =_xlfn.XLOOKUP(A7,#REF!,#REF!,"",0,1) -> #REF! | D7: L3917618 | F7: L3917544
A8: L3917619 | B8: =_xlfn.XLOOKUP(A8,#REF!,#REF!,"",0,1) -> #REF! | D8: L3917619 | F8: L3917618
A9: L3917786 | B9: =_xlfn.XLOOKUP(A9,#REF!,#REF!,"",0,1) -> #REF! | D9: L3917786 | F9: L3917619
A10: L3918046 | B10: =_xlfn.XLOOKUP(A10,#REF!,#REF!,"",0,1) -> #REF! | D10: L3918046 | F10: L3917786
A11: L3918086 | B11: =_xlfn.XLOOKUP(A11,#REF!,#REF!,"",0,1) -> #REF! | D11: L3918086 | F11: L3918046
A12: L3918256 | B12: =_xlfn.XLOOKUP(A12,#REF!,#REF!,"",0,1) -> #REF! | D12: L3918256 | F12: L3918086
... A179: L2404494 | B179: =_xlfn.XLOOKUP(A179,#REF!,#REF!,"",0,1) -> #REF! | D179: L2404494 | F179: L3924297
F180: L3924298
F181: L3924303
F182: L3924306
F183: L39N00306
F184: L2404162
F185: L2404214
F186: L2404208
F187: L2404270
F188: L2404254
F189: L2404425
F190: L2404424
F191: L2404489
... F193: L2404494

Sheet Power Query Table
A1: Invoice # | B1: Name | C1: Email | D1: Invoice From | E1: Invoice To | F1: Raised on | G1: Due on | H1: Paid On | I1: Total Tax | J1: Column2 | K1: Column3 | L1: Column1 | M1: Total | N1: Paid | O1: Attribute | P1: Value
A2: L3924638 | B2: JEB ENGINEERING SERVICES LLP | C2: nb729@jbs.cam.ac.uk | D2: 45839 | E2: 45870 | F2: 45866.692 | G2: 45873.692 | H2: 45860 | I2: 88 | J2: =Table1__4[[#This Row],[Value]]*0.2 -> 88 | K2: =Table1__4[[#This Row],[Total Tax]]-Table1__4[[#This Row],[Column2]] -> 0 | L2: =Table1__4[[#This Row],[Value]]*1.2 -> 528 | M2: 528 | N2: TRUE | O2: 4211-3011 - L39 Hot Desk Membership (2024) | P2: 440
I3: =SUM(Table1__4[Total Tax]) -> 88 | M3: =SUM(Table1__4[Total]) -> 528

Sheet Membership invoices

Sheet Mapping
A2: Mapping
A3: 4211-3011 | B3: c0000035 | C3: Lvl 39
A4: 4211-4011 | B4: c0000035 | C4: Lvl 39
A5: 4211-2011 | B5: c0000035 | C5: Lvl 39
A6: 5275-9500 | B6: c0000035 | C6: Lvl 39
A7: 4211-9031 | B7: c0000035 | C7: Lvl 39
A8: 2521-1112 | B8: c0000035 | C8: Lvl 39
A9: 4211-1011 | B9: c0000008 | C9: Lvl 24
A10: 2723-0621 | B10: c0000035 | C10: Lvl 39
A11: 4211201 - | B11: c0000035 | C11: Lvl 39
A12: 4211404 - | B12: c0000035 | C12: Lvl 39
A13: 4211118 - | B13: c0000035 | C13: Lvl 39
A14: 4211708 - | B14: c0000035 | C14: Lvl 39
... A24: 4211-7061 | B24: c0000035 | C24: Lvl 39
A25: 2521830 -
A26: 4211303 - | B26: c0000035 | C26: Lvl 39
A27: 2521830/L
A28: 4211409 - | B28: c0000035 | C28: Lvl 39
A29: 4211202 - | B29: c0000035 | C29: Lvl 39
A30: 4211801 - | B30: c0000035 | C30: Lvl 39

Sheet Recoverability
F1: KEY
F2: Code | G2: DEP | H2: RENT | I2: GEN | J2: CON | K2: DIR | L2: EW | M2: TS | N2: AE | O2: PART | P2: INS | Q2: RES | R2: SF | S2: SC | T2: RP | U2: UN | V2: EST | W2: DEPTDS
B3: Property Recoverability Aid as at 8 March 2025 | F3: Description | G3: Deposits | H3: Rent | I3: General | J3: Construction | K3: Direct Tenant Charges | L3: East Wintergarden | M3: Tenant Services | N3: Arts & Events | O3: Public Art | P3: Insurance | Q3: Reserve Fund | R3: Sinking Fund | S3: Service Charge | T3: Retail Promotions | U3: Unallocated Cash | V3: Estate | W3: Custodial Deposits
F4: Note: This report shows the recoverabilities set up for each property/entity.
B5: Property | C5: Prop Description | D5: Recovery
B6: c001 | C6: Canary Wharf Limited | D6: GEN^UN^CON
B7: c002 | C7: Canary Wharf Contractors Limited | D7: CON^GEN
B8: c003 | C8: Heron Quays Properties Limited | D8: GEN^UN^EW
B9: c004 | C9: Canary Wharf Investments Limited | D9: GEN^UN^RENT
B10: c005 | C10: Cabot Place Limited | D10: GEN^UN^RENT
B11: c006 | C11: Canary Wharf Management Limited | D11: GEN^UN^SC^TS^RP
B12: c007 | C12: South Quay Properties Limited | D12: GEN^UN
B13: c008 | C13: DORMANT - Seven Westferry Circus Limited | D13: GEN^UN
B14: c014 | C14: Canary Wharf Investments (Two) Limited | D14: GEN^UN
B15: c015 | C15: Canary Wharf Investments (Three) | D15: GEN^UN
B16: c016 | C16: DORMANT - First Tower T1 Limited | D16: GEN^UN
... B69: c091 | C69: Canary Wharf Group plc | D69: GEN^UN^RENT
B70: c0a2 | C70: CLOSED - Canary Wharf Finance Limited
B71: c0a4 | C71: CW Properties DS7B Limited | D71: GEN^UN
B72: c0a5 | C72: CW Leasing DS7B Limited | D72: GEN^UN^RENT^INS
B73: c0a7 | C73: CW Properties DS7F Limited | D73: GEN^UN
B74: c0a8 | C74: CW Leasing DS7F Limited | D74: GEN^UN^RENT^INS
B75: c0ac | C75: CLOSED - One Canada Square (Retail) Unit Trust | D75: GEN^UN
B76: c0af | C76: CLOSED - Canada Place (Retail) Unit Trust | D76: GEN^UN
B77: c0ai | C77: CLOSED - Cabot Place (Retail) Unit Trust | D77: GEN^UN
B78: c0al | C78: CLOSED - Canada Place Mall (Retail) Unit Trust | D78: GEN^UN
B79: c0ao | C79: CLOSED - Jubilee Place (Retail) Unit Trust | D79: GEN^UN
B80: c0ar | C80: 10 Cabot Square I Unit Trust | D80: GEN^UN
B81: c0au | C81: 10 Cabot Square II Unit Trust | D81: GEN^UN
B82: c0ax | C82: 20 Cabot Square I Unit Trust | D82: GEN^UN
... B85: c0ba | C85: 20 Cabot Square II Unit Trust | D85: GEN^UN
B86: c0bd | C86: CLOSED - Canary Wharf Finance III Limited
B87: c0bf | C87: 10 Cabot Square I Unit Trust LP Limited | D87: GEN^UN
B88: c0bg | C88: 10 Cabot Square I Unit Trust GP Limited | D88: GEN^UN
B89: c0bh | C89: 10 Cabot Square I Unit Trust SLP | D89: GEN^UN
B90: c0bj | C90: 10 Cabot Square II Unit Trust LP Limited | D90: GEN^UN
B91: c0bk | C91: 10 Cabot Square II Unit Trust GP Limited | D91: GEN^UN
B92: c0bl | C92: 10 Cabot Square II Unit Trust SLP | D92: GEN^UN
B93: c0bm | C93: 20 Cabot Square I Unit Trust LP Limited | D93: GEN^UN
B94: c0bn | C94: 20 Cabot Square I Unit Trust GP Limited | D94: GEN^UN
B95: c0bp | C95: 20 Cabot Square I Unit Trust SLP | D95: GEN^UN
B96: c0bq | C96: 20 Cabot Square II Unit Trust LP Limited | D96: GEN^UN
B97: c0br | C97: 20 Cabot Square II Unit Trust GP Limited | D97: GEN^UN
B98: c0bs | C98: 20 Cabot Square II Unit Trust SLP | D98: GEN^UN
... B228: c0gt | C228: DORMANT - L39 Limited | D228: GEN^UN
B229: c0gu | C229: CLOSED - Canary Wharf Grosvenor Place Limited
B230: c0gv | C230: Canary Wharf NQO Investments Limited | D230: GEN^UN
B231: c0gw | C231: Canary Wharf NQO Holdings Limited | D231: GEN^UN
B232: c0gx | C232: Canary Wharf (CS Park Pavilion) Limited | D232: GEN^UN
B233: c0gy | C233: CW Holdco (B2) Limited | D233: GEN^UN
B234: c0gz | C234: CW Properties (B2) Limited | D234: GEN^UN
B235: c0h6 | C235: DORMANT - Heron Quays Holdings (HQ1) Limited | D235: GEN^UN
B236: c0h7 | C236: DORMANT - Heron Quays (HQ1) T1 Limited | D236: GEN^UN
B237: c0h8 | C237: DORMANT - Heron Quays (HQ1) T2 Limited | D237: GEN^UN
B238: c0h9 | C238: HQCB Properties (HQ1) Limited | D238: GEN^UN
B239: c0ha | C239: Heron Quays West (Pavilion) Limited | D239: GEN^UN^CON
B240: c0hb | C240: DORMANT - Canary Wharf NFLA Limited | D240: GEN^UN
B241: c0hc | C241: Canary Wharf Residential Management Limited | D241: GEN^UN
... B250: c0hm | C250: CW Water Square Development Company Limited | D250: CON
B251: c0hn | C251: CLOSED - Canary Wharf Holdings Euston Limited
B252: c0hp | C252: CLOSED - Canary Wharf Euston GP Holdings Limited
B253: c0hq | C253: CLOSED - Canary Wharf Euston LP Limited
B254: c0hr | C254: CLOSED - Euston Station Development GP Limited
B255: c0hs | C255: CLOSED - Euston Station Development Limited Partnership
B256: c0ht | C256: Canary Wharf Group Residential Limited | D256: GEN^UN
B257: c0hu | C257: DORMANT - CW Development Consulting Limited | D257: GEN^UN
B258: c0hv | C258: Canary Wharf (Finance Lessor) Limited | D258: GEN^UN
B259: c0hw | C259: CLOSED - Canary Wharf (Earl's Court) Limited | D259: GEN^UN
B260: c0hx | C260: DORMANT - South London Procurement Network Limited | D260: GEN^UN
B261: c0hy | C261: Canary Wharf Energy Company Limited | D261: GEN^UN
B262: c0j0 | C262: DORMANT - Heron Quays Holdings (HQ2) Limited | D262: GEN^UN
B263: c0j1 | C263: DORMANT - Heron Quays (HQ2) Limited | D263: GEN^UN
B264: c0j2 | C264: DORMANT - Heron Quays (HQ2) T1 Limited | D264: GEN^UN
B265: c0j3 | C265: DORMANT - Heron Quays (HQ2) T2 Limited | D265: GEN^UN
B266: c0j4 | C266: CLOSED - HQCB Properties (HQ2) Limited | D266: GEN^UN
B267: c0j5 | C267: DORMANT - Heron Quays Holdings (HQ3) Limited | D267: GEN^UN
... B295: c0k0 | C295: Heron Quays Holdings (HQ 4) Limited | D295: GEN^UN
B296: c0k1 | C296: CLOSED - Heron Quays (HQ 4) Limited
B297: c0k4 | C297: CLOSED - HQCB Properties (HQ4) Limited
B298: c0k5 | C298: CLOSED - Heron Quays Holdings (HQ5) Limited | D298: GEN^UN
B299: c0k6 | C299: CLOSED - Heron Quays (HQ5) Limited | D299: GEN^UN
B300: c0k9 | C300: CLOSED - HQCB Properties (HQ5) Limited
B301: c0ka | C301: DORMANT - Braeburn Estates (B6/7) T1 Limited | D301: GEN^UN
B302: c0kb | C302: DORMANT - Braeburn Estates (B6/7) T2 Limited | D302: GEN^UN
B303: c0kc | C303: Braeburn Estates Retail Limited | D303: GEN^UN
B304: c0kd | C304: Braeburn Estates (Hungerford) Limited | D304: GEN^UN^CON
B305: c0ke | C305: Braeburn Estates (Lollard Street) Limited | D305: CON
B306: c0kg | C306: Braeburn Estates (B3) Residential Limited | D306: GEN^UN
B307: c0kh | C307: Braeburn Estates (B4A) Residential Limited | D307: GEN^UN
B308: c0kj | C308: Braeburn Estates (B4B) Residential Limited | D308: GEN^UN
B309: c0kk | C309: Braeburn Estates (B5) Residential Limited | D309: GEN^UN
B310: c0kl | C310: Braeburn Estates (B6/7) Residential Limited | D310: GEN^UN
B311: c0km | C311: Braeburn Estates (B3) Retail Limited | D311: GEN^UN
B312: c0kn | C312: Braeburn Estates (AH) Limited | D312: GEN^UN
... B319: c0kx | C319: Braeburn Estates (Retail) Limited Partnership | D319: GEN^UN
B320: c0l0 | C320: CLOSED - South Quay Amenities Limited
B321: c0l1 | C321: CLOSED - South Quay Management Limited | D321: GEN^UN
B322: c0l2 | C322: HQCB Investments Limited | D322: GEN^UN
B323: c0l3 | C323: Armoric Limited | D323: GEN^UN
B324: c0l5 | C324: Bannerclose Limited | D324: GEN^UN
...

Sheet IC Codes
C3: IC Segment Tree as at 14 Mar 2025 | H3: Note: The codes below require the IC segment to be populated with the entity/property the intercompany is with
C4: GL Acc | D4: Code | E4: Description | H4: GL Acc Paired | I4: GL Acc Description 2
C5: 10516011 | D5: 1051-6011 | E5: Internal Investments - historic cost | F5: IC Required | J5: IC Required
C6: 10516019 | D6: 1051-6019 | E6: Internal Investments - Provision | F6: IC Required | J6: IC Required
C7: 10516021 | D7: 1051-6021 | E7: Internal Investments - profit accrual | F7: IC Required | J7: IC Required
C8: 10516031 | D8: 1051-6031 | E8: Internal Investments - parternship loans | F8: IC Required | J8: IC Required
C9: 10516041 | D9: 1051-6041 | E9: Internal Investments - share of revaluation | F9: IC Required | J9: IC Required
C10: 11080113 | D10: 1108-0113 | E10: Construction: construction management (CM) fees | F10: IC Required | J10: IC Required
C11: 11080114 | D11: 1108-0114 | E11: Construction: development management (DM) fees | F11: IC Required | J11: IC Required
C12: 11800033 | D12: 1180-0033 | E12: IC Non-Certified Accruals flow (with jobs) - IN | F12: IC Required | H12: 1180-0034 | I12: IC Non-Certified Accruals flow (with jobs) - OUT | J12: IC Required
C13: 11800034 | D13: 1180-0034 | E13: IC Non-Certified Accruals flow (with jobs) - OUT | F13: IC Required | H13: 1180-0033 | I13: IC Non-Certified Accruals flow (with jobs) - IN | J13: IC Required
C14: 11800040 | D14: 1180-0040 | E14: IC WIP Transfers (with jobs) - IN | F14: IC Required | H14: 1180-0041 | I14: I/C WIP Transfers | J14: IC Required
C15: 11800041 | D15: 1180-0041 | E15: I/C WIP Transfers | F15: IC Required | H15: 1180-0040 | I15: IC WIP Transfers (with jobs) - IN | J15: IC Required
C16: 11800042 | D16: 1180-0042 | E16: I/C WIP Transfers (no jobs) | F16: IC Required | J16: IC Required
C17: 11800043 | D17: 1180-0043 | E17: I/C WIP Billing (with jobs) | F17: IC Required | H17: 1180-0044 | I17: IC WIP Billing (with jobs) - OUT | J17: IC Required
C18: 11800044 | D18: 1180-0044 | E18: IC WIP Billing (with jobs) - OUT | F18: IC Required | H18: 1180-0043 | I18: I/C WIP Billing (with jobs) | J18: IC Required
C19: 13151000 | D19: 1315-1000 | E19: Interco-setoffs | F19: IC Required | J19: IC Required
C20: 13151001 | D20: 1315-1001 | E20: Interco - Current (receivable) | F20: IC Required | H20: 1315-1001 | I20: Interco - Current (receivable) | J20: IC Required
C21: 13151002 | D21: 1315-1002 | E21: Interco - Loan Interest (receivable) | F21: IC Required | H21: 2415-1002 | I21: Interco - Loan Interest (payable) | J21: IC Required
C22: 13151003 | D22: 1315-1003 | E22: Interco - Loans (receivable) | F22: IC Required | H22: 2415-1003 | I22: Interco - Loans (payable) | J22: IC Required
C23: 13151006 | D23: 1315-1006 | E23: Interco - Loans Swap Adj. (receivable) | F23: IC Required | H23: 2415-1006 | I23: Interco - Loans Swap Adj. (payable) | J23: IC Required
C24: 13151007 | D24: 1315-1007 | E24: Interco - Loan Fees (receivable) | F24: IC Required | H24: 2415-1007 | I24: Interco - Loan Fees (payable) | J24: IC Required
C25: 13151009 | D25: 1315-1009 | E25: Provision against IC debtor | F25: IC Required | J25: IC Required
C26: 13151011 | D26: 1315-1011 | E26: Interco - Finance Rents Payments (receivable) | F26: IC Required | H26: 2415-1011 | I26: Interco - Finance Rents Payments (payable) | J26: IC Required
C27: 13151021 | D27: 1315-1021 | E27: Interco - Finance Lease SSAP21 (receivable) | F27: IC Required | H27: 2415-1021 | I27: Interco - Finance Lease SSAP21 (payable) | J27: IC Required
C28: 13151031 | D28: 1315-1031 | E28: Interco - Finance Lease Creditor (receivable) | F28: IC Required | H28: 2415-1031 | I28: Interco - Finance Lease Creditor (payable) | J28: IC Required
C29: 13151041 | D29: 1315-1041 | E29: Interco – Discount on acquisition (receivable) | F29: IC Required | H29: 2415-1041 | I29: Interco – Discount on acquisition (payable) | J29: IC Required
C30: 13152001 | D30: 1315-2001 | E30: Interco - IC Incentives (receivable) | F30: IC Required | H30: 2415-2001 | I30: Interco - IC Incentives (payable) | J30: IC Required
C31: 13153001 | D31: 1315-3001 | E31: Interco - Voids accruals | F31: IC Required | H31: 1315-3001 | I31: Interco - Voids accruals | J31: IC Required
C32: 13154001 | D32: 1315-4001 | E32: Interco - Wood Wharf contribution agreement | F32: IC Required | J32: IC Required
C33: 13161601 | D33: 1316-1601 | E33: Interco - Other Loans (receivable) | F33: IC Required | H33: 2416-1601 | I33: Interco - Other Loans (payable) | J33: IC Required
C34: 13161611 | D34: 1316-1611 | E34: Interco - Other Loan Interest (receivable) | F34: IC Required | H34: 2416-1611 | I34: Interco Loan Interest (payable) | J34: IC Required
C35: 13161621 | D35: 1316-1621 | E35: Interco - Other Loan Fees (receivable) | F35: IC Required | H35: 2416-1621 | I35: Interco - Other Loan Fees (payable) | J35: IC Required
C36: 13161631 | D36: 1316-1631 | E36: Interco - Other Loan Fair Value Adjustment (receivable) | F36: IC Required | H36: 2416-1631 | I36: Interco - Other Loan Fair Value Adjustment (payable) | J36: IC Required
C37: 13161641 | D37: 1316-1641 | E37: Interco - Other Loan Provision (receivable) | F37: IC Required | H37: 2416-1641 | I37: Interco - Other Loan Provision (payable) | J37: IC Required
C38: 13161661 | D38: 1316-1661 | E38: Interco - Eurobonds (receivable) | F38: IC Required | H38: 2416-1661 | I38: Interco - Eurobonds (payable) | J38: IC Required
C39: 13161662 | D39: 1316-1662 | E39: IC Loans (receivable) – Spens | F39: IC Required | H39: 2416-1662 | I39: IC Loans (payable) – Spens | J39: IC Required
C40: 15059001 | D40: 1505-9001 | E40: IC PP - Office and Retail Rents | F40: IC Required | H40: 2723-9001 | I40: Deferred Intercompany - Office and Retail Rents | J40: IC Required
C41: 15059011 | D41: 1505-9011 | E41: IC PP - Ground Rents | F41: IC Required | H41: 2723-9011 | I41: Deferred Intercompany - Ground Rents | J41: IC Required
C42: 15059021 | D42: 1505-9021 | E42: IC PP - UITF28 REnt Adjustments | F42: IC Required | H42: 2723-9021 | I42: Deferred Intercompany - UITF28 Rent Adjustments | J42: IC Required
C43: 15059031 | D43: 1505-9031 | E43: IC PP - Car Park Rents | F43: IC Required | H43: 2723-9031 | I43: Deferred Intercompany - Car Park Rents | J43: IC Required
C44: 15059041 | D44: 1505-9041 | E44: IC PP - Service Charge | F44: IC Required | H44: 2723-9041 | I44: Deferred Intercompany - Service Charge | J44: IC Required
... C47: 15059071 | D47: 1505-9071 | E47: IC PP - Provision of services mgmt fee | F47: IC Required | H47: 2723-9071 | I47: Deferred Intercompany - provision of services mgt fee | J47: IC Required
C48: 24151001 | D48: 2415-1001 | E48: Interco - Current (payable) | F48: IC Required | J48: IC Required
C49: 24151002 | D49: 2415-1002 | E49: Interco - Loan Interest (payable) | F49: IC Required | H49: 1315-1002 | I49: Interco - Loan Interest (receivable) | J49: IC Required
C50: 24151003 | D50: 2415-1003 | E50: Interco - Loans (payable) | F50: IC Required | H50: 1315-1003 | I50: Interco - Loans (receivable) | J50: IC Required
C51: 24151006 | D51: 2415-1006 | E51: Interco - Loans Swap Adj. (payable) | F51: IC Required | H51: 1315-1006 | I51: Interco - Loans Swap Adj. (receivable) | J51: IC Required
C52: 24151007 | D52: 2415-1007 | E52: Interco - Loan Fees (payable) | F52: IC Required | H52: 1315-1007 | I52: Interco - Loan Fees (receivable) | J52: IC Required
C53: 24151011 | D53: 2415-1011 | E53: Interco - Finance Rents Payments (payable) | F53: IC Required | H53: 1315-1011 | I53: Interco - Finance Rents Payments (receivable) | J53: IC Required
C54: 24151021 | D54: 2415-1021 | E54: Interco - Finance Lease SSAP21 (payable) | F54: IC Required | H54: 1315-1021 | I54: Interco - Finance Lease SSAP21 (receivable) | J54: IC Required
C55: 24151031 | D55: 2415-1031 | E55: Interco - Finance Lease Creditor (payable) | F55: IC Required | H55: 1315-1031 | I55: Interco - Finance Lease Creditor (receivable) | J55: IC Required
C56: 24151041 | D56: 2415-1041 | E56: Interco – Discount on acquisition (payable) | F56: IC Required | H56: 1315-1041 | I56: Interco – Discount on acquisition (receivable) | J56: IC Required
C57: 24152001 | D57: 2415-2001 | E57: Interco - IC Incentives (payable) | F57: IC Required | H57: 1315-2001 | I57: Interco - IC Incentives (receivable) | J57: IC Required
C58: 24161601 | D58: 2416-1601 | E58: Interco - Other Loans (payable) | F58: IC Required | H58: 1316-1601 | I58: Interco - Other Loans (receivable) | J58: IC Required
C59: 24161611 | D59: 2416-1611 | E59: Interco Loan Interest (payable) | F59: IC Required | H59: 1316-1611 | I59: Interco - Other Loan Interest (receivable) | J59: IC Required
C60: 24161612 | D60: 2416-1612 | E60: Interco loan accrued interest (payable) | F60: IC Required | J60: IC Required
C61: 24161621 | D61: 2416-1621 | E61: Interco - Other Loan Fees (payable) | F61: IC Required | H61: 1316-1621 | I61: Interco - Other Loan Fees (receivable) | J61: IC Required
C62: 24161631 | D62: 2416-1631 | E62: Interco - Other Loan Fair Value Adjustment (payable) | F62: IC Required | H62: 1316-1631 | I62: Interco - Other Loan Fair Value Adjustment (receivable) | J62: IC Required
C63: 24161641 | D63: 2416-1641 | E63: Interco - Other Loan Provision (payable) | F63: IC Required | H63: 1316-1641 | I63: Interco - Other Loan Provision (receivable) | J63: IC Required
C64: 24161661 | D64: 2416-1661 | E64: Interco - Eurobonds (payable) | F64: IC Required | H64: 1316-1661 | I64: Interco - Eurobonds (receivable) | J64: IC Required
C65: 24161662 | D65: 2416-1662 | E65: IC Loans (payable) – Spens | F65: IC Required | H65: 1316-1662 | I65: IC Loans (receivable) – Spens | J65: IC Required
C66: 27231071 | D66: 2723-1071 | E66: Deferred Parking - Inter - Company Recharge | F66: IC Required | J66: IC Required
C67: 27239001 | D67: 2723-9001 | E67: Deferred Intercompany - Office and Retail Rents | F67: IC Required | H67: 1505-9001 | I67: IC PP - Office and Retail Rents | J67: IC Required
C68: 27239011 | D68: 2723-9011 | E68: Deferred Intercompany - Ground Rents | F68: IC Required | H68: 1505-9011 | I68: IC PP - Ground Rents | J68: IC Required
C69: 27239021 | D69: 2723-9021 | E69: Deferred Intercompany - UITF28 Rent Adjustments | F69: IC Required | H69: 1505-9021 | I69: IC PP - UITF28 REnt Adjustments | J69: IC Required
C70: 27239031 | D70: 2723-9031 | E70: Deferred Intercompany - Car Park Rents | F70: IC Required | H70: 1505-9031 | I70: IC PP - Car Park Rents | J70: IC Required
C71: 27239041 | D71: 2723-9041 | E71: Deferred Intercompany - Service Charge | F71: IC Required | H71: 1505-9041 | I71: IC PP - Service Charge | J71: IC Required
C72: 27239051 | D72: 2723-9051 | E72: Deferred Intercompany - Service Charge Voids | F72: IC Required | H72: 1505-9051 | I72: IC PP - Service Charge Voids | J72: IC Required
C73: 27239061 | D73: 2723-9061 | E73: Deferred Intercompany - Management Fee (Income) | F73: IC Required | H73: 1505-9061 | I73: IC PP - Management Fee (Cost) | J73: IC Required
C74: 27239071 | D74: 2723-9071 | E74: Deferred Intercompany - provision of services mgt fee | F74: IC Required | H74: 1505-9071 | I74: IC PP - Provision of services mgmt fee | J74: IC Required
C75: 27239081 | D75: 2723-9081 | E75: Deferred Asset management fee | F75: IC Required | J75: IC Required
C76: 27239091 | D76: 2723-9091 | E76: Deferred IC – Contribution Agreements | F76: IC Required | J76: IC Required
C77: 28201012 | D77: 2820-1012 | E77: Provision against onerous interco leases | F77: IC Required | J77: IC Required
C78: 41151011 | D78: 4115-1011 | E78: Interco - Office and Retail Rents (Turnover) | F78: IC Required | H78: 5115-1011 | I78: Interco - Office and Retail Rents (cost of sales) | J78: IC Required
C79: 41151012 | D79: 4115-1012 | E79: Interco - Carparking Rents | F79: IC Required | H79: 5115-1012 | I79: Interco - Carparking Rents (cost of sales) | J79: IC Required
C80: 41151021 | D80: 4115-1021 | E80: Interco - Ground Rents (turnover) | F80: IC Required | H80: 5115-1021 | I80: Interco - Ground Rents (cost of sales) | J80: IC Required
C81: 41151031 | D81: 4115-1031 | E81: Interco - UITF28 Rent Adjustments (turnover) | F81: IC Required | H81: 5115-1031 | I81: Interco - UITF28 Rent Adjustments (cost of sales) | J81: IC Required
C82: 41151042 | D82: 4115-1042 | E82: IC Residential BTR Rent (Turnover) | F82: IC Required | H82: 5115-1042 | I82: IC Residential BTR Rent (Cost of Sales) | J82: IC Required
C83: 41151051 | D83: 4115-1051 | E83: Interco - Service Charge (turnover) | F83: IC Required | H83: 5115-1051 | I83: Interco - Service Charge (cost of sales) | J83: IC Required
C84: 41151061 | D84: 4115-1061 | E84: Interco - Service Charge Voids (turnover) | F84: IC Required | H84: 5115-1061 | I84: Interco - Service Charge Voids (cost of sales) | J84: IC Required
C85: 41151062 | D85: 4115-1062 | E85: Service Charge Voids – Property to Entity | F85: IC Required | J85: IC Required
C86: 41151071 | D86: 4115-1071 | E86: Interco - Sale of Properties (turnover) | F86: IC Required | H86: 5115-1071 | I86: Interco - Sale of Properties (cost of sales) | J86: IC Required
C87: 41151081 | D87: 4115-1081 | E87: Interco - Construction Turnover (turnover) | F87: IC Required | H87: 5115-1081 | I87: Interco - Construction Turnover (cost of sales) | J87: IC Required
C88: 41151082 | D88: 4115-1082 | E88: Interco - Turnover markup | F88: IC Required | J88: IC Required
C89: 41151091 | D89: 4115-1091 | E89: Interco - IC lease incentives (turnover) | F89: IC Required | H89: 5115-1091 | I89: Interco - IC lease incentives (cost of sales) | J89: IC Required
C90: 41411001 | D90: 4141-1001 | E90: Interco - Construction cost recharges (turnover) | F90: IC Required | H90: 5141-1001 | I90: Interco - Construction cost recharges (cost of sales) | J90: IC Required
C91: 41411002 | D91: 4141-1002 | E91: 1% Fee re IC - Construction cost recharges (turnover) | F91: IC Required | J91: IC Required
C92: 41421001 | D92: 4142-1001 | E92: Interco - CM - Construction Management Fee | F92: IC Required | H92: 5142-1001 | I92: Interco - CM - Construction Management Fee | J92: IC Required
C93: 41431001 | D93: 4143-1001 | E93: Interco - DM - Development Management Fee | F93: IC Required | H93: 5143-1001 | I93: Interco - DM - Development Management Fee | J93: IC Required
C94: 41441001 | D94: 4144-1001 | E94: IC - Asset Management Fee | F94: IC Required | H94: 6000-1001 | I94: IC - Asset Management Fee | J94: IC Required
C95: 41501421 | D95: 4150-1421 | E95: Interco - Commercial Heat Sales | F95: IC Required | H95: 5150-1421 | I95: Interco - Commercial Heat Costs | J95: IC Required
C96: 41501422 | D96: 4150-1422 | E96: Interco - Commercial Heat Sales (NFL) | F96: IC Required | H96: 5150-1422 | I96: Interco - Commercial Heat Costs (NFL) | J96: IC Required
C97: 41501431 | D97: 4150-1431 | E97: Interco - Residential Heat Sales | F97: IC Required | H97: 5150-1431 | I97: Interco - Residential Heat Costs | J97: IC Required
C98: 41501432 | D98: 4150-1432 | E98: Interco - Residential Heat Sales (NFL) | F98: IC Required | H98: 5150-1432 | I98: Interco - Residential Heat Costs (NFL) | J98: IC Required
C99: 41501621 | D99: 4150-1621 | E99: Interco - Electrical Sales | F99: IC Required | H99: 5150-1621 | I99: Interco - Electrical Costs | J99: IC Required
C100: 41501622 | D100: 4150-1622 | E100: Interco - Electrical Sales (NFL) | F100: IC Required | H100: 5150-1622 | I100: Interco - Electrical Costs (NFL) | J100: IC Required
C101: 41501721 | D101: 4150-1721 | E101: Interco - Non Energy Sales | F101: IC Required | H101: 5150-1721 | I101: Interco - Non Energy Costs | J101: IC Required
C102: 41501722 | D102: 4150-1722 | E102: Interco - Non Energy Sales (NFL) | F102: IC Required | H102: 5150-1722 | I102: Interco - Non Energy Costs (NFL) | J102: IC Required
C103: 41751411 | D103: 4175-1411 | E103: IC Rent - Own occupied space | F103: IC Required | H103: 5175-1411 | I103: IC Rent - Own occupied space | J103: IC Required
C104: 41751511 | D104: 4175-1511 | E104: IC Rent – Lvl 39 occupied space | F104: IC Required | H104: 5175-1511 | I104: IC Rent – Lvl 39 occupied space | J104: IC Required
...

Sheet Budget
B2: Budget Segment Accounts as at 8 March 2025
B4: Account | C4: Acct Description | D4: Expense Type / Budget Segment | E4: Validation Rules | F4: Budget Tree
B5: 1021-2461 | C5: Plant and Machinery | D5: IT^Information Technology^Unexpected Costs^IC Ad Hoc | E5: 1021-2461 | F5: 1021-2461
B6: 1021-2481 | C6: Computer Hardware | D6: IT^Information Technology^Treasury^Unexpected Costs^IC Ad Hoc | E6: 1021-2481 | F6: 1021-2481
B7: 1021-2488 | C7: Disaster Recovery Costs | D7: IT^Unexpected Costs^IC Ad Hoc | E7: 1021-2488 | F7: 1021-2488
B8: 1021-2501 | C8: Computer Software | D8: IT^Treasury^Unexpected Costs^IC Ad Hoc | E8: 1021-2501 | F8: 1021-2501
B9: 1031-2421 | C9: Fixtures and Equipment | D9: Facilities^Corp Bldg Serv^VRML O/H^Lvl39^Level39^Unexpected Costs^IC Ad Hoc | E9: 1031-2421 | F9: 1031-2421
B10: 1031-2501 | C10: F&F cost oracle legacy | D10: Corp Bldg Serv^Unexpected Costs^IC Ad Hoc | E10: 1031-2501 | F10: 1031-2501
B11: 1108-1320 | C11: Tenant Inducement Costs | D11: Office Leasing^Leasing Office^Leasing Retail^Unexpected Costs^IC Ad Hoc^Retail Projects | E11: 1108-1320 | F11: 1108-1320
B12: 1108-5012 | C12: Tenant Construction Retail (without job) | D12: CapCon^CapCon Retail^Retail Works^Unexpected Costs^IC Ad Hoc^Retail Projects | E12: 1108-5012 | F12: 1108-5012
B13: 1108-5013 | C13: Tenant Construction Office (with job) | D13: Leasing Office^Unexpected Costs^IC Ad Hoc | E13: 1108-5013 | F13: 1108-5013
B14: 1404-9311 | C14: FFL - Recharges / Claims | D14: ELBP/BL/SLPN^IC Ad Hoc^Unexpected Costs | E14: 1404-9311 | F14: 1404-9311
B15: 1404-9321 | C15: FFL - Marketing and Publicity | D15: ELBP/BL/SLPN^IC Ad Hoc^Unexpected Costs | E15: 1404-9321 | F15: 1404-9321
... B79: 5781-3111 | C79: IPTV costs | D79: Telecoms^Unexpected Costs^IC Ad Hoc^Information Technology | E79: 5781-3111 | F79: 5781-3111
B80: 6154-5411 | C80: INACITVE: Planning General | D80: Unexpected Costs^IC Ad Hoc^Leasing Office^Feas/Model/Plan | F80: 6154-5411
B81: 6154-6811 | C81: Memberships | D81: CWRML O/H^Unexpected Costs^IC Ad Hoc^Corp Affairs^Mktg Vertus^Leasing Retail^Customer Experience^VRML O/H^Sustainability^Vertus Mgmt | E81: 6154-6811 | F81: 6154-6811
B82: 6162-1000 | C82: Total Payroll Costs - Overheads | D82: Unexpected Costs^Payroll^IC Ad Hoc | E82: 6162-1000 | F82: 6162-1000
B83: 6162-1411 | C83: BUPA/Life Assurance/Disability | D83: CWRML O/H^Payroll^Mktg Vertus^VRML O/H^IC Ad Hoc | E83: 6162-1411 | F83: 6162-1411
B84: 6162-1501 | C84: Redundancy | D84: Unexpected Costs^Payroll^IC Ad Hoc | F84: 6162-1501
B85: 6162-2911 | C85: LTIP Share Option Scheme | D85: Unexpected Costs^Payroll^IC Ad Hoc | E85: 6162-2911 | F85: 6162-2911
B86: 6162-5821 | C86: Employee professional subscriptions | D86: CWRML O/H^Unexpected Costs^CoSec^Leasing Office^Legal^Payroll^Ppl and Dev^Press Office^Donations^Leasing Resi^Mktg Office^Mktg Resi^Mktg Retail^Mktg Vertus^Leasing Retail^Corp Bldg Serv^Tax^VRML O/H^IT^Insurance^Sustainability^Accounts^IC Ad Hoc | E86: 6162-5821 | F86: 6162-5821
B87: 6162-5911 | C87: Hiring and Recruitment | D87: Unexpected Costs^Payroll^Ppl and Dev^VRML O/H^Vertus Mgmt^IC Ad Hoc | E87: 6162-5911 | F87: 6162-5911
B88: 6162-6111 | C88: Payroll - QIA Non Exec Fees | D88: Unexpected Costs^Payroll^Reward and Benefits^IC Ad Hoc | E88: 6162-6111 | F88: 6162-6111
B89: 6163-0311 | C89: Audit Fees - Statutory | D89: Unexpected Costs^Accounts^IC Ad Hoc | E89: 6163-0311 | F89: 6163-0311
B90: 6163-0371 | C90: External valuation fees | D90: Valuations^Unexpected Costs^Prop Valuations^Accounts^IC Ad Hoc | E90: 6163-0371 | F90: 6163-0371
B91: 6163-0411 | C91: Taxation Fees | D91: Tax^IC Ad Hoc | E91: 6163-0411 | F91: 6163-0411
B92: 6163-0606 | C92: Legal - Dev Misc | D92: Legal^IC Ad Hoc | E92: 6163-0606 | F92: 6163-0606
B93: 6163-0811 | C93: Bank Charges (Admin expenses) | D93: CWRML O/H^Payroll^Mktg Vertus^VRML O/H^IC Ad Hoc | E93: 6163-0811 | F93: 6163-0811
B94: 6163-5011 | C94: Professional Fees | D94: Rates^Legal^Payroll^Ppl and Dev^Mktg Vertus^VRML O/H^Accounts^IC Ad Hoc | E94: 6163-5011 | F94: 6163-5011
B95: 6164-0411 | C95: Subscriptions/Manuals | D95: CoSec^Legal^Ppl and Dev^Tax^IT^IC Ad Hoc | E95: 6164-0411 | F95: 6164-0411
B96: 6164-0711 | C96: Software Maintenance | D96: Unexpected Costs^VRML O/H^IT^Vertus Mgmt^IC Ad Hoc | E96: 6164-0711 | F96: 6164-0711
... B122: 9110-0111 | C122: UK Corporation Tax | D122: HMRC^Taxation^Unexpected Costs^IC Ad Hoc | E122: 9110-0111 | F122: 9110-0111

Sheet VAT
A3: Tax Rate Lookup | B3: Vat Rates | C3: AP Tax Types | D3: AR Tax Tran Types | E3: Tax Rates Codes
A4: ukstd20 | B4: 0.2 | C4: purch | D4: sales | E4: ukstd20
A5: ukred5 | B5: 0.05 | C5: purch | D5: sales | E5: ukred5
A6: ukzero | B6: 0 | C6: purch | D6: sales | E6: ukzero
A7: exempt | B7: Exempt | C7: expurch | D7: exsales
A8: outside | B8: Outside | C8: oospurch | D8: oossales

Sheet CoA
B4: Chart of Accounts as at 14 Mar 2025
B6: Account | C6: Account Name | D6: Normal | E6: Acct | F6: Rpt | H6: Line | I6: Offset | J6: Hold-For | K6: Accrual | L6: Total | M6: Flags
D7: Balance | E7: Type | F7: Type | G7: Margin | H7: Adv. | I7: Account | J7: Account | K7: Account | L7: Account
B8: 1000-0000 | C8: BALANCE SHEET | D8: Debit | E8: Head | F8: Bal | G8: 0 | H8: 0
B9: 1001-0000 | C9: FIXED ASSET | D9: Debit | E9: Head | F9: Bal | G9: 0 | H9: 0 | L9: 1099-9999
B10: 1002-0000 | C10: Tangible Fixed Asset | D10: Debit | E10: Head | F10: Bal | G10: 0 | H10: 0 | L10: 1049-9999
B11: 1010-0000 | C11: Land and Buildings | D11: Debit | E11: Head | F11: Bal | G11: 0 | H11: 0 | L11: 1019-9999
B12: 1011-2301 | C12: Interest in Freehold Land | D12: Debit | E12: Reg | F12: Bal | G12: 3 | H12: 0 | L12: 1019-9999
B13: 1011-2302 | C13: Disposal of interest in Freehold Land | D13: Debit | E13: Reg | F13: Bal | G13: 3 | H13: 0 | L13: 1019-9999
B14: 1011-2303 | C14: Provision against Freehold Land | D14: Debit | E14: Reg | F14: Bal | G14: 3 | H14: 0 | L14: 1019-9999
B15: 1011-2304 | C15: Properties Under Construction | D15: Debit | E15: Reg | F15: Bal | G15: 3 | H15: 1 | L15: 1019-9999
B16: 1011-2305 | C16: Development Properties | D16: Debit | E16: Reg | F16: Bal | G16: 3 | H16: 1 | L16: 1019-9999
B17: 1011-2310 | C17: Revaluation of Freehold Land | D17: Debit | E17: Reg | F17: Bal | G17: 3 | H17: 0 | L17: 1019-9999
B18: 1011-2311 | C18: Interest in Property | D18: Debit | E18: Reg | F18: Bal | G18: 3 | H18: 0 | L18: 1019-9999
B19: 1011-2312 | C19: Revaluation of Leasehold Property | D19: Debit | E19: Reg | F19: Bal | G19: 3 | H19: 0 | L19: 1019-9999
B20: 1011-2313 | C20: Disposal of interest in investment property | D20: Debit | E20: Reg | F20: Bal | G20: 3 | H20: 0 | L20: 1019-9999
... B116: 1108-0000 | C116: WIP | D116: Debit | E116: Head | F116: Bal | G116: 0 | H116: 0 | L116: 1199-9999
B117: 1108-0015 | C117: WIP Markup (with job) | D117: Debit | E117: Reg | F117: Bal | G117: 3 | H117: 1 | L117: 1199-9999 | M117: WIP
B118: 1108-0016 | C118: WIP Markup (no job) | D118: Debit | E118: Reg | F118: Bal | G118: 3 | H118: 1 | L118: 1199-9999
B119: 1108-0044 | C119: INACTIVE: IC WIP Billing (with jobs) - OUT | D119: Debit | E119: Reg | F119: Bal | G119: 3 | H119: 1 | L119: 1199-9999 | M119: Exclude, WIP
B120: 1108-0111 | C120: Construction: Base Building | D120: Debit | E120: Reg | F120: Bal | G120: 3 | H120: 1 | L120: 1199-9999 | M120: WIP
B121: 1108-0112 | C121: Construction retention | D121: Debit | E121: Reg | F121: Bal | G121: 0 | H121: 1 | L121: 1199-9999 | M121: WIP
B122: 1108-0113 | C122: Construction: construction management (CM) fees | D122: Debit | E122: Reg | F122: Bal | G122: 3 | H122: 1 | L122: 1199-9999 | M122: WIP
B123: 1108-0114 | C123: Construction: development management (DM) fees | D123: Debit | E123: Reg | F123: Bal | G123: 3 | H123: 1 | L123: 1199-9999 | M123: WIP
B124: 1108-0211 | C124: Construction Under Brackendown Contract | D124: Debit | E124: Reg | F124: Bal | G124: 3 | H124: 0 | L124: 1199-9999
B125: 1108-0411 | C125: Inter-Company Property Disposals | D125: Debit | E125: Reg | F125: Bal | G125: 3 | H125: 1 | L125: 1199-9999
B126: 1108-0511 | C126: External Property Disposals | D126: Debit | E126: Reg | F126: Bal | G126: 3 | H126: 0 | L126: 1199-9999
B127: 1108-0521 | C127: External Property Disposals - SSAP9 | D127: Debit | E127: Reg | F127: Bal | G127: 3 | H127: 0 | L127: 1199-9999
B128: 1108-0611 | C128: IC WIP purchases | D128: Debit | E128: Reg | F128: Bal | G128: 3 | H128: 1 | L128: 1199-9999
B129: 1108-0811 | C129: WIP transfers to property (Buildings) | D129: Debit | E129: Reg | F129: Bal | G129: 3 | H129: 0 | L129: 1199-9999
B130: 1108-0821 | C130: WIP - Year end transfers to fixed assets | D130: Debit | E130: Reg | F130: Bal | G130: 3 | H130: 0 | L130: 1199-9999
B131: 1108-0911 | C131: External Property Purchases | D131: Debit | E131: Reg | F131: Bal | G131: 3 | H131: 0 | L131: 1199-9999
B132: 1108-1011 | C132: External land purchases | D132: Debit | E132: Reg | F132: Bal | G132: 3 | H132: 0 | L132: 1199-9999
B133: 1108-1021 | C133: British Waterways Density payment | D133: Debit | E133: Reg | F133: Bal | G133: 3 | H133: 0 | L133: 1199-9999
B134: 1108-1031 | C134: Stamp Duty Land Tax (SDLT) | D134: Debit | E134: Reg | F134: Bal | G134: 3 | H134: 0 | L134: 1199-9999
B135: 1108-1041 | C135: British Waterways Density agreement fees | D135: Debit | E135: Reg | F135: Bal | G135: 3 | H135: 0 | L135: 1199-9999
B136: 1108-1051 | C136: ECC costs to infrastructure | D136: Debit | E136: Reg | F136: Bal | G136: 3 | H136: 0 | L136: 1199-9999
B137: 1108-1061 | C137: S106 agreement | D137: Debit | E137: Reg | F137: Bal | G137: 3 | H137: 1 | L137: 1199-9999 | M137: WIP
B138: 1108-1071 | C138: SSAP 9 Legal Fees | D138: Debit | E138: Reg | F138: Bal | G138: 3 | H138: 0 | L138: 1199-9999
B139: 1108-1081 | C139: Acquisition legal fees | D139: Debit | E139: Reg | F139: Bal | G139: 3 | H139: 0 | L139: 1199-9999
B140: 1108-1091 | C140: Carillion payments HQW and NFL | D140: Debit | E140: Reg | F140: Bal | G140: 3 | H140: 0 | L140: 1199-9999
B141: 1108-1101 | C141: Mayoral CIL Payment | D141: Debit | E141: Reg | F141: Bal | G141: 3 | H141: 1 | L141: 1199-9999 | M141: WIP
B142: 1108-1121 | C142: Land Registry | D142: Debit | E142: Reg | F142: Bal | G142: 3 | H142: 0 | L142: 1199-9999
B143: 1108-1211 | C143: Contribution to JLE | D143: Debit | E143: Reg | F143: Bal | G143: 3 | H143: 0 | L143: 1199-9999
B144: 1108-1221 | C144: Contribution from JLE | D144: Debit | E144: Reg | F144: Bal | G144: 3 | H144: 0 | L144: 1199-9999
B145: 1108-1311 | C145: Tenant inducement: takeover properties | D145: Debit | E145: Reg | F145: Bal | G145: 3 | H145: 0 | L145: 1199-9999
B146: 1108-1320 | C146: Tenant Inducement Costs | D146: Debit | E146: Reg | F146: Bal | G146: 3 | H146: 1 | L146: 1199-9999
B147: 1108-1321 | C147: UITF28 WIP | D147: Debit | E147: Reg | F147: Bal | G147: 3 | H147: 0 | L147: 1199-9999
B148: 1108-1331 | C148: Aldersgate St UITF 28 WIP adj | D148: Debit | E148: Reg | F148: Bal | G148: 3 | H148: 0 | L148: 1199-9999
B149: 1108-1341 | C149: TI on lease backs | D149: Debit | E149: Reg | F149: Bal | G149: 3 | H149: 0 | L149: 1199-9999
B150: 1108-1411 | C150: Broadgate payments | D150: Debit | E150: Reg | F150: Bal | G150: 3 | H150: 0 | L150: 1199-9999
B151: 1108-1501 | C151: Leadenhall Construction Costs | D151: Debit | E151: Reg | F151: Bal | G151: 3 | H151: 1 | L151: 1199-9999
B152: 1108-1711 | C152: License fees | D152: Debit | E152: Reg | F152: Bal | G152: 3 | H152: 0 | L152: 1199-9999
B153: 1108-2001 | C153: Costs re Aldersgate St. trans to provisions | D153: Debit | E153: Reg | F153: Bal | G153: 3 | H153: 0 | L153: 1199-9999
B154: 1108-3111 | C154: Crossrail WIP trf | D154: Debit | E154: Reg | F154: Bal | G154: 3 | H154: 0 | L154: 1199-9999
B155: 1108-5011 | C155: Tenant Construction | D155: Debit | E155: Reg | F155: Bal | G155: 3 | H155: 1 | L155: 1199-9999 | M155: WIP
B156: 1108-5012 | C156: Tenant Construction Retail (without job) | D156: Debit | E156: Reg | F156: Bal | G156: 3 | H156: 1 | L156: 1199-9999
B157: 1108-5013 | C157: Tenant Construction Office (with job) | D157: Debit | E157: Reg | F157: Bal | G157: 3 | H157: 1 | L157: 1199-9999 | M157: WIP
B158: 1108-5014 | C158: Tenant Construction Office (without job) | D158: Debit | E158: Reg | F158: Bal | G158: 3 | H158: 1 | L158: 1199-9999
B159: 1108-5021 | C159: Construction MEES (without job) | D159: Debit | E159: Reg | F159: Bal | G159: 3 | H159: 1 | L159: 1199-9999
B160: 1108-5111 | C160: Dilapidation and moves | D160: Debit | E160: Reg | F160: Bal | G160: 3 | H160: 0 | L160: 1199-9999
B161: 1108-5211 | C161: SSAP 9 Debtor | D161: Debit | E161: Reg | F161: Bal | G161: 3 | H161: 0 | L161: 1199-9999
B162: 1108-6011 | C162: Land Purchases | D162: Debit | E162: Reg | F162: Bal | G162: 3 | H162: 0 | L162: 1199-9999
B163: 1108-7011 | C163: Fitting out Costs Recoverable | D163: Debit | E163: Reg | F163: Bal | G163: 3 | H163: 0 | L163: 1199-9999
B164: 1113-2011 | C164: Tenant Inducements | D164: Debit | E164: Reg | F164: Bal | G164: 3 | H164: 0 | L164: 1199-9999
B165: 1122-0311 | C165: Advance Lease Payments | D165: Debit | E165: Reg | F165: Bal | G165: 3 | H165: 0 | L165: 1199-9999
B166: 1180-0011 | C166: Construction Accruals (no Jobs) | D166: Debit | E166: Reg | F166: Bal | G166: 3 | H166: 1 | L166: 1199-9999
B167: 1180-0012 | C167: Construction Accruals (with Jobs) | D167: Debit | E167: Reg | F167: Bal | G167: 3 | H167: 1 | L167: 1199-9999 | M167: WIP
B168: 1180-0021 | C168: Tenant Construction Accruals | D168: Debit | E168: Reg | F168: Bal | G168: 3 | H168: 0 | L168: 1199-9999
B169: 1180-0031 | C169: CM Certified Accruals | D169: Debit | E169: Reg | F169: Bal | G169: 3 | H169: 1 | L169: 1199-9999 | M169: WIP
B170: 1180-0032 | C170: CM Non-Certified Accruals | D170: Debit | E170: Reg | F170: Bal | G170: 3 | H170: 1 | L170: 1199-9999 | M170: WIP
B171: 1180-0033 | C171: IC Non-Certified Accruals flow (with jobs) - IN | D171: Debit | E171: Reg | F171: Bal | G171: 3 | H171: 1 | L171: 1199-9999 | M171: WIP
B172: 1180-0034 | C172: IC Non-Certified Accruals flow (with jobs) - OUT | D172: Debit | E172: Reg | F172: Bal | G172: 3 | H172: 1 | L172: 1199-9999 | M172: WIP
B173: 1180-0040 | C173: IC WIP Transfers (with jobs) - IN | D173: Debit | E173: Reg | F173: Bal | G173: 3 | H173: 1 | L173: 1199-9999 | M173: WIP
B174: 1180-0041 | C174: IC WIP Transfers (with jobs) - OUT | D174: Debit | E174: Reg | F174: Bal | G174: 3 | H174: 1 | L174: 1199-9999 | M174: WIP
B175: 1180-0042 | C175: IC WIP Transfers (no jobs) | D175: Debit | E175: Reg | F175: Bal | G175: 3 | H175: 1 | L175: 1199-9999
B176: 1180-0043 | C176: IC WIP Billing (with jobs) - IN | D176: Debit | E176: Reg | F176: Bal | G176: 3 | H176: 1 | L176: 1199-9999 | M176: WIP
B177: 1180-0044 | C177: IC WIP Billing (with jobs) - OUT | D177: Debit | E177: Reg | F177: Bal | G177: 3 | H177: 1 | L177: 1199-9999 | M177: WIP
B178: 1180-0051 | C178: Capitalised interest - Specific | D178: Debit | E178: Reg | F178: Bal | G178: 3 | H178: 1 | L178: 1199-9999
B179: 1180-0052 | C179: Capitalised interest - General | D179: Debit | E179: Reg | F179: Bal | G179: 3 | H179: 1 | L179: 1199-9999
B180: 1180-0061 | C180: WIP costs legal fees | D180: Debit | E180: Reg | F180: Bal | G180: 3 | H180: 0 | L180: 1199-9999
B181: 1180-0062 | C181: Marketing Cost WIP Transfer | D181: Debit | E181: Reg | F181: Bal | G181: 3 | H181: 1 | L181: 1199-9999 | M181: WIP
B182: 1180-0071 | C182: Wood Wharf contribution agreement accrual | D182: Debit | E182: Reg | F182: Bal | G182: 3 | H182: 0 | L182: 1199-9999
B183: 1180-0081 | C183: Braeburn Estate costs | D183: Debit | E183: Reg | F183: Bal | G183: 3 | H183: 0 | L183: 1199-9999
B184: 1180-0082 | C184: Braeburn Estate setup costs | D184: Debit | E184: Reg | F184: Bal | G184: 3 | H184: 1 | L184: 1199-9999
B185: 1180-0091 | C185: WW Resi/Vertus Setup Costs | D185: Debit | E185: Reg | F185: Bal | G185: 3 | H185: 1 | L185: 1199-9999
B186: 1180-1010 | C186: Affordable Housing Receipts | D186: Debit | E186: Reg | F186: Bal | G186: 3 | H186: 1 | L186: 1199-9999
B187: 1180-1011 | C187: WIP costs finance contra fees | D187: Debit | E187: Reg | F187: Bal | G187: 3 | H187: 0 | L187: 1199-9999
B188: 1181-0111 | C188: SQ West CPO costs | D188: Debit | E188: Reg | F188: Bal | G188: 3 | H188: 0 | L188: 1199-9999
B189: 1181-0121 | C189: HQ West BWB costs | D189: Debit | E189: Reg | F189: Bal | G189: 3 | H189: 0 | L189: 1199-9999
B190: 1181-0131 | C190: HQ West BWB payment | D190: Debit | E190: Reg | F190: Bal | G190: 3 | H190: 0 | L190: 1199-9999
B191: 1184-9911 | C191: Irrecoverable VAT-Post 20.06.93 Construction | D191: Debit | E191: Reg | F191: Bal | G191: 3 | H191: 1 | L191: 1199-9999 | M191: WIP
B192: 1184-9921 | C192: Irrecoverable VAT | D192: Debit | E192: Reg | F192: Bal | G192: 3 | H192: 1 | L192: 1199-9999
B193: 1195-0411 | C193: Release of WIP on sale of apartments | D193: Debit | E193: Reg | F193: Bal | G193: 3 | H193: 1 | L193: 1199-9999
B194: 1195-0412 | C194: Expense non-capital items in construction budgets | D194: Debit | E194: Reg | F194: Bal | G194: 3 | H194: 1 | L194: 1199-9999
B195: 1198-0111 | C195: Provision Against WIP (WIP) | D195: Debit | E195: Reg | F195: Bal | G195: 3 | H195: 0 | L195: 1199-9999
B196: 1199-0011 | C196: WIP transfers to property (WIP) | D196: Debit | E196: Reg | F196: Bal | G196: 3 | H196: 0 | L196: 1199-9999
B197: 1199-0021 | C197: WIP transfers to prepayments | D197: Debit | E197: Reg | F197: Bal | G197: 3 | H197: 0 | L197: 1199-9999
B198: 1199-0031 | C198: WIP oracle legacy | D198: Debit | E198: Reg | F198: Bal | G198: 0 | H198: 0 | L198: 1199-9999
B199: 1199-0041 | C199: WIP non migrated projects | D199: Debit | E199: Reg | F199: Bal | G199: 0 | H199: 1 | L199: 1199-9999
...

Sheet Company Info
B3: Company Information as at 8 March 2025
B5: Oracle Code | C5: IM Entity | D5: Owner Code | E5: Owner Name | F5: Tax Authority | G5: Tax Point | H5: Currency | I5: Rate Provider | J5: Sales Type | K5: Purchase Type | L5: Registration Number | M5: TAX Last Reported on | N5: TAX Reporting Frequency | O5: Fiscal Entity Code | P5: Fiscal Entity | Q5: Commerce Reg Number | R5: City Of Registration
B6: =RIGHT($C6,2) -> 01 | C6: ="c0"&RIGHT($D6,2) -> c001 | D6: o001 | E6: Canary Wharf Limited | F6: uk | G6: Invoice | H6: gbp | I6: blo(spot) | J6: sales | K6: purch | L6: 512639654 | M6: 2/1/2025 | N6: Monthly | O6: vgrp001 | P6: VAT Group - Canary Wharf Limited | Q6: 01971312 | R6: UK
B7: =RIGHT($C7,2) -> 02 | C7: ="c0"&RIGHT($D7,2) -> c002 | D7: o002 | E7: Canary Wharf Contractors Limited | F7: uk | G7: Invoice | H7: gbp | I7: blo(spot) | J7: sales | K7: purch | L7: 507034774 | M7: 2/1/2025 | N7: Monthly | Q7: 02352250 | R7: UK
B8: =RIGHT($C8,2) -> 03 | C8: ="c0"&RIGHT($D8,2) -> c003 | D8: o003 | E8: Heron Quays Properties Limited | F8: uk | G8: Invoice | H8: gbp | I8: blo(spot) | J8: sales | K8: purch | L8: 512639654 | M8: 2/1/2025 | N8: Monthly | O8: vgrp001 | P8: VAT Group - Canary Wharf Limited | Q8: 02276627 | R8: UK
B9: =RIGHT($C9,2) -> 04 | C9: ="c0"&RIGHT($D9,2) -> c004 | D9: o004 | E9: Canary Wharf Investments Limited | F9: uk | G9: Invoice | H9: gbp | I9: blo(spot) | J9: sales | K9: purch | L9: 512639654 | M9: 2/1/2025 | N9: Monthly | O9: vgrp001 | P9: VAT Group - Canary Wharf Limited | Q9: 02127410 | R9: UK
B10: =RIGHT($C10,2) -> 05 | C10: ="c0"&RIGHT($D10,2) -> c005 | D10: o005 | E10: Cabot Place Limited | F10: uk | G10: Invoice | H10: gbp | I10: blo(spot) | J10: sales | K10: purch | L10: 549233923 | M10: 1/1/2025 | N10: Quarterly | Q10: 02548110 | R10: UK
B11: =RIGHT($C11,2) -> 06 | C11: ="c0"&RIGHT($D11,2) -> c006 | D11: o006 | E11: Canary Wharf Management Limited | F11: uk | G11: Invoice | H11: gbp | I11: blo(spot) | J11: sales | K11: purch | L11: 512639654 | M11: 2/1/2025 | N11: Monthly | O11: vgrp001 | P11: VAT Group - Canary Wharf Limited | Q11: 02067510 | R11: UK
B12: =RIGHT($C12,2) -> 07 | C12: ="c0"&RIGHT($D12,2) -> c007 | D12: o007 | E12: South Quay Properties Limited | F12: uk | G12: Invoice | H12: gbp | I12: blo(spot) | J12: sales | K12: purch | L12: 161772993 | M12: 2/1/2025 | N12: Quarterly | Q12: 02830131 | R12: UK
B13: =RIGHT($C13,2) -> 08 | C13: ="c0"&RIGHT($D13,2) -> c008 | D13: o008 | E13: Seven Westferry Circus Limited | F13: uk | G13: n/a | H13: gbp | I13: blo(spot) | M13: 2/1/2025 | N13: Monthly | Q13: 02732071 | R13: UK
B14: =RIGHT($C14,2) -> 14 | C14: ="c0"&RIGHT($D14,2) -> c014 | D14: o014 | E14: Canary Wharf Investments (Two) Limited | F14: uk | G14: n/a | H14: gbp | I14: blo(spot) | M14: 2/1/2025 | N14: Monthly | Q14: 02863616 | R14: UK
B15: =RIGHT($C15,2) -> 15 | C15: ="c0"&RIGHT($D15,2) -> c015 | D15: o015 | E15: Canary Wharf Investments (Three) | F15: uk | G15: n/a | H15: gbp | I15: blo(spot) | M15: 2/1/2025 | N15: Monthly | Q15: 02455786 | R15: UK
B16: =RIGHT($C16,2) -> 16 | C16: ="c0"&RIGHT($D16,2) -> c016 | D16: o016 | E16: First Tower T1 Limited | F16: uk | G16: n/a | H16: gbp | I16: blo(spot) | M16: 2/1/2025 | N16: Monthly | Q16: 02550906 | R16: UK
B17: =RIGHT($C17,2) -> 17 | C17: ="c0"&RIGHT($D17,2) -> c017 | D17: o017 | E17: First Tower T2 Limited | F17: uk | G17: n/a | H17: gbp | I17: blo(spot) | M17: 2/1/2025 | N17: Monthly | Q17: 02558070 | R17: UK
B18: =RIGHT($C18,2) -> 18 | C18: ="c0"&RIGHT($D18,2) -> c018 | D18: o018 | E18: First Tower GP(1) Limited | F18: uk | G18: n/a | H18: gbp | I18: blo(spot) | M18: 2/1/2025 | N18: Monthly | Q18: SC132920 | R18: SCOTTISH
B19: =RIGHT($C19,2) -> 19 | C19: ="c0"&RIGHT($D19,2) -> c019 | D19: o019 | E19: First Tower GP(2) Limited | F19: uk | G19: n/a | H19: gbp | I19: blo(spot) | M19: 2/1/2025 | N19: Monthly | Q19: SC132921 | R19: SCOTTISH
B20: =RIGHT($C20,2) -> 1a | C20: ="c0"&RIGHT($D20,2) -> c01a | D20: o01a | E20: SBP1 Sarl | F20: uk | G20: Invoice | H20: gbp | I20: blo(spot) | J20: sales | K20: purch | L20: 194324890 | M20: 12/1/2024 | N20: Quarterly
B21: =RIGHT($C21,2) -> 1b | C21: ="c0"&RIGHT($D21,2) -> c01b | D21: o01b | E21: Braeburn Estates (B4A) Limited Partnership Propman Co | F21: uk | G21: Invoice | H21: gbp | I21: blo(spot) | J21: sales | K21: purch | L21: 188636260 | M21: 12/1/2024 | N21: Quarterly | O21: vgrp0jg | P21: VAT Group - Braeburn Estates B4A (GP) Limited
B22: =RIGHT($C22,2) -> 1c | C22: ="c0"&RIGHT($D22,2) -> c01c | D22: o01c | E22: Braeburn Estates (B4B) Limited Partnership Propman Co | F22: uk | G22: Invoice | H22: gbp | I22: blo(spot) | J22: sales | K22: purch | L22: 188636554 | M22: 12/1/2024 | N22: Quarterly | O22: vgrp0jm | P22: VAT Group - Braeburn Estates B4B (GP) Limited
B23: =RIGHT($C23,2) -> 1d | C23: ="c0"&RIGHT($D23,2) -> c01d | D23: o01d | E23: Braeburn Estates (B5) Limited Partnership Propman Co | F23: uk | G23: Invoice | H23: gbp | I23: blo(spot) | J23: sales | K23: purch | L23: 188637649 | M23: 2/1/2025 | N23: Monthly | O23: vgrp0js | P23: VAT Group - Braeburn Estates B5 (GP) Limited
B24: =RIGHT($C24,2) -> 1e | C24: ="c0"&RIGHT($D24,2) -> c01e | D24: o01e | E24: Braeburn Estates (B6/7) Limited Partnership Propman Co | F24: uk | G24: Invoice | H24: gbp | I24: blo(spot) | J24: sales | K24: purch | L24: 188641271 | M24: 12/1/2024 | N24: Quarterly | O24: vgrp0jx | P24: VAT Group - Braeburn Estates B6/7 (GP) Limited
B25: =RIGHT($C25,2) -> 1f | C25: ="c0"&RIGHT($D25,2) -> c01f | D25: o01f | E25: Braeburn Estates Management Company Limited Propman Co | F25: uk | G25: Invoice | H25: gbp | I25: blo(spot) | J25: sales | K25: purch | L25: 210439253 | M25: 12/1/2024 | N25: Quarterly | O25: vgrp0ja | P25: VAT Group - Braeburn Estates Management Company Limited
B26: =RIGHT($C26,2) -> 1g | C26: ="c0"&RIGHT($D26,2) -> c01g | D26: o01g | E26: Braeburn Estates Retail Limited Propman Co | F26: uk | G26: Invoice | H26: gbp | I26: blo(spot) | J26: sales | K26: purch | L26: 210278054 | M26: 12/1/2024 | N26: Quarterly | O26: vgrp0kc | P26: VAT Group - Braeburn Estates Retail Limited
B27: =RIGHT($C27,2) -> 1h | C27: ="c0"&RIGHT($D27,2) -> c01h | D27: o01h | E27: SBP2 Sarl | F27: uk | G27: Invoice | H27: gbp | I27: blo(spot) | J27: sales | K27: purch | L27: 194324009 | M27: 12/1/2024 | N27: Quarterly
B28: =RIGHT($C28,2) -> 1k | C28: ="c0"&RIGHT($D28,2) -> c01k | D28: o01k | E28: Vertus 10 George Street Limited Propman Co | F28: uk | G28: Invoice | H28: gbp | I28: blo(spot) | J28: sales | K28: purch | L28: 343829287 | M28: 12/1/2024 | N28: Quarterly | O28: vgrp0rc | P28: VAT Group - Vertus 10 George Street Limited
B29: =RIGHT($C29,2) -> 1l | C29: ="c0"&RIGHT($D29,2) -> c01l | D29: o01l | E29: Vertus 8 Water Street Limited Propman Co | F29: uk | G29: Invoice | H29: gbp | I29: blo(spot) | J29: sales | K29: purch | L29: 346742875 | M29: 12/1/2024 | N29: Quarterly | O29: vgrp0rb | P29: VAT Group - Vertus 8 Water Street Limited
B30: =RIGHT($C30,2) -> 1m | C30: ="c0"&RIGHT($D30,2) -> c01m | D30: o01m | E30: Vertus Newfoundland Place Limited Propman Co | F30: uk | G30: Invoice | H30: gbp | I30: blo(spot) | J30: sales | K30: purch | L30: 387523660 | M30: 12/1/2024 | N30: Quarterly | O30: vgrp0vm | P30: VAT Group - Vertus Residential Management Limited
B31: =RIGHT($C31,2) -> 1n | C31: ="c0"&RIGHT($D31,2) -> c01n | D31: o01n | E31: Wood Wharf Estate Management Limited Propman Co | F31: uk | G31: Invoice | H31: gbp | I31: blo(spot) | J31: sales | K31: purch | L31: 208904508 | M31: 12/1/2024 | N31: Quarterly
B32: =RIGHT($C32,2) -> 1p | C32: ="c0"&RIGHT($D32,2) -> c01p | D32: o01p | E32: Canary Wharf Residential Management Limited Propman Co | F32: uk | G32: n/a | H32: gbp | I32: blo(spot) | M32: 2/1/2025 | N32: Monthly
B33: =RIGHT($C33,2) -> 1r | C33: ="c0"&RIGHT($D33,2) -> c01r | D33: o01r | E33: CW One Park Drive Limited Propman Co | F33: uk | G33: Invoice | H33: gbp | I33: blo(spot) | J33: sales | K33: purch | L33: 384584749 | M33: 12/1/2024 | N33: Quarterly | O33: vgrp0rg | P33: VAT Group - CW Wood Wharf Residential StaffCo Ltd
B34: =RIGHT($C34,2) -> 1s | C34: ="c0"&RIGHT($D34,2) -> c01s | D34: o01s | E34: CW 10 Park Drive Limited Propman Co | F34: uk | G34: Invoice | H34: gbp | I34: blo(spot) | J34: sales | K34: purch | L34: 384584749 | M34: 12/1/2024 | N34: Quarterly | O34: vgrp0rg | P34: VAT Group - CW Wood Wharf Residential StaffCo Ltd
B35: =RIGHT($C35,2) -> 32 | C35: ="c0"&RIGHT($D35,2) -> c032 | D35: o032 | E35: First Tower Limited Partnership | F35: uk | G35: n/a | H35: gbp | I35: blo(spot) | M35: 2/1/2025 | N35: Monthly | Q35: LP004097 | R35: UK
B36: =RIGHT($C36,2) -> 34 | C36: ="c0"&RIGHT($D36,2) -> c034 | D36: o034 | E36: Canary Wharf Investments (Four) Limited | F36: uk | G36: n/a | H36: gbp | I36: blo(spot) | M36: 2/1/2025 | N36: Monthly | Q36: 02388957 | R36: UK
B37: =RIGHT($C37,2) -> 38 | C37: ="c0"&RIGHT($D37,2) -> c038 | D37: o038 | E37: CWE SPV SUPER HCo Limited | F37: uk | G37: n/a | H37: gbp | I37: blo(spot) | M37: 2/1/2025 | N37: Monthly | Q37: 03123346 | R37: UK
B38: =RIGHT($C38,2) -> 39 | C38: ="c0"&RIGHT($D38,2) -> c039 | D38: o039 | E38: CWE SPV HCo Limited | F38: uk | G38: n/a | H38: gbp | I38: blo(spot) | M38: 2/1/2025 | N38: Monthly | Q38: 03123311 | R38: UK
B39: =RIGHT($C39,2) -> 42 | C39: ="c0"&RIGHT($D39,2) -> c042 | D39: o042 | E39: CWE SPVc Limited | F39: uk | G39: n/a | H39: gbp | I39: blo(spot) | M39: 2/1/2025 | N39: Monthly | Q39: 03123343 | R39: UK
B40: =RIGHT($C40,2) -> 45 | C40: ="c0"&RIGHT($D40,2) -> c045 | D40: o045 | E40: CWE SPVf Limited | F40: uk | G40: n/a | H40: gbp | I40: blo(spot) | M40: 2/1/2025 | N40: Monthly | Q40: 03123299 | R40: UK
B41: =RIGHT($C41,2) -> 46 | C41: ="c0"&RIGHT($D41,2) -> c046 | D41: o046 | E41: CWE SPVg Limited | F41: uk | G41: n/a | H41: gbp | I41: blo(spot) | M41: 2/1/2025 | N41: Monthly | Q41: 03123286 | R41: UK
B42: =RIGHT($C42,2) -> 48 | C42: ="c0"&RIGHT($D42,2) -> c048 | D42: o048 | E42: CWC SPV HCo Limited | F42: uk | G42: n/a | H42: gbp | I42: blo(spot) | M42: 2/1/2025 | N42: Monthly | Q42: 03123064 | R42: UK
B43: =RIGHT($C43,2) -> 50 | C43: ="c0"&RIGHT($D43,2) -> c050 | D43: o050 | E43: CWC SPVa Limited | F43: uk | G43: Invoice | H43: gbp | I43: blo(spot) | J43: sales | K43: purch | L43: 751849895 | M43: 2/1/2025 | N43: Quarterly | Q43: 03123292 | R43: UK
B44: =RIGHT($C44,2) -> 56 | C44: ="c0"&RIGHT($D44,2) -> c056 | D44: o056 | E44: CWC SPVc Limited | F44: uk | G44: n/a | H44: gbp | I44: blo(spot) | M44: 2/1/2025 | N44: Monthly | Q44: 03253119 | R44: UK
B45: =RIGHT($C45,2) -> 57 | C45: ="c0"&RIGHT($D45,2) -> c057 | D45: o057 | E45: CWC SPVd Limited | F45: uk | G45: n/a | H45: gbp | I45: blo(spot) | M45: 2/1/2025 | N45: Monthly | Q45: 03302741 | R45: UK
B46: =RIGHT($C46,2) -> 58 | C46: ="c0"&RIGHT($D46,2) -> c058 | D46: o058 | E46: CWC SPVe Limited | F46: uk | G46: n/a | H46: gbp | I46: blo(spot) | M46: 2/1/2025 | N46: Monthly | Q46: 03302707 | R46: UK
B47: =RIGHT($C47,2) -> 59 | C47: ="c0"&RIGHT($D47,2) -> c059 | D47: o059 | E47: Cabot Place Holdings Limited | F47: uk | G47: n/a | H47: gbp | I47: blo(spot) | M47: 2/1/2025 | N47: Monthly | Q47: 03302749 | R47: UK
B48: =RIGHT($C48,2) -> 60 | C48: ="c0"&RIGHT($D48,2) -> c060 | D48: o060 | E48: CWCB Investments (Car Parks) Limited | F48: uk | G48: n/a | H48: gbp | I48: blo(spot) | M48: 2/1/2025 | N48: Monthly | Q48: 03302682 | R48: UK
B49: =RIGHT($C49,2) -> 63 | C49: ="c0"&RIGHT($D49,2) -> c063 | D49: o063 | E49: Canary Wharf Holdings (B4) Limited | F49: uk | G49: n/a | H49: gbp | I49: blo(spot) | M49: 2/1/2025 | N49: Monthly | Q49: 03666935 | R49: UK
B50: =RIGHT($C50,2) -> 64 | C50: ="c0"&RIGHT($D50,2) -> c064 | D50: o064 | E50: Canary Wharf (B4) Limited | F50: uk | G50: n/a | H50: gbp | I50: blo(spot) | M50: 2/1/2025 | N50: Monthly | Q50: 03666185 | R50: UK
B51: =RIGHT($C51,2) -> 65 | C51: ="c0"&RIGHT($D51,2) -> c065 | D51: o065 | E51: Canary Wharf Contractors (B4) Limited | F51: uk | G51: n/a | H51: gbp | I51: blo(spot) | M51: 2/1/2025 | N51: Monthly | Q51: 03511556 | R51: UK
B52: =RIGHT($C52,2) -> 66 | C52: ="c0"&RIGHT($D52,2) -> c066 | D52: o066 | E52: Canada Place Limited | F52: uk | G52: Invoice | H52: gbp | I52: blo(spot) | J52: sales | K52: purch | L52: 761031565 | M52: 2/1/2025 | N52: Quarterly | Q52: 03666325 | R52: UK
B53: =RIGHT($C53,2) -> 68 | C53: ="c0"&RIGHT($D53,2) -> c068 | D53: o068 | E53: Canary.co.uk Limited | F53: uk | G53: n/a | H53: gbp | I53: blo(spot) | M53: 2/1/2025 | N53: Monthly | Q53: 03666582 | R53: UK
B54: =RIGHT($C54,2) -> 69 | C54: ="c0"&RIGHT($D54,2) -> c069 | D54: o069 | E54: CWCB Leasing (DS6) Limited | F54: uk | G54: n/a | H54: gbp | I54: blo(spot) | M54: 2/1/2025 | N54: Monthly | Q54: 03941692 | R54: UK
B55: =RIGHT($C55,2) -> 75 | C55: ="c0"&RIGHT($D55,2) -> c075 | D55: o075 | E55: Canary Wharf Contractors (B5) Limited | F55: uk | G55: n/a | H55: gbp | I55: blo(spot) | M55: 2/1/2025 | N55: Monthly | Q55: 03442704 | R55: UK
B56: =RIGHT($C56,2) -> 76 | C56: ="c0"&RIGHT($D56,2) -> c076 | D56: o076 | E56: Canary Wharf Holdings (B5) Limited | F56: uk | G56: n/a | H56: gbp | I56: blo(spot) | M56: 2/1/2025 | N56: Monthly | Q56: 03442716 | R56: UK
B57: =RIGHT($C57,2) -> 77 | C57: ="c0"&RIGHT($D57,2) -> c077 | D57: o077 | E57: Canary Wharf (B5) Limited | F57: uk | G57: n/a | H57: gbp | I57: blo(spot) | M57: 2/1/2025 | N57: Monthly | Q57: 03442708 | R57: UK
B58: =RIGHT($C58,2) -> 78 | C58: ="c0"&RIGHT($D58,2) -> c078 | D58: o078 | E58: Canary Wharf (B5) T1 Limited | F58: uk | G58: n/a | H58: gbp | I58: blo(spot) | M58: 2/1/2025 | N58: Monthly | Q58: 03442705 | R58: UK
B59: =RIGHT($C59,2) -> 79 | C59: ="c0"&RIGHT($D59,2) -> c079 | D59: o079 | E59: Canary Wharf (B5) T2 Limited | F59: uk | G59: n/a | H59: gbp | I59: blo(spot) | M59: 2/1/2025 | N59: Monthly | Q59: 03442710 | R59: UK
B60: =RIGHT($C60,2) -> 80 | C60: ="c0"&RIGHT($D60,2) -> c080 | D60: o080 | E60: Canary Wharf Contractors (DS6) Limited | F60: uk | G60: n/a | H60: gbp | I60: blo(spot) | M60: 2/1/2025 | N60: Monthly | Q60: 03194822 | R60: UK
B61: =RIGHT($C61,2) -> 82 | C61: ="c0"&RIGHT($D61,2) -> c082 | D61: o082 | E61: Canary Wharf (DS6) T2 Limited | F61: uk | G61: n/a | H61: gbp | I61: blo(spot) | M61: 2/1/2025 | N61: Monthly | Q61: 03320957 | R61: UK
B62: =RIGHT($C62,2) -> 83 | C62: ="c0"&RIGHT($D62,2) -> c083 | D62: o083 | E62: Canary Wharf (DS6) T1 Limited | F62: uk | G62: n/a | H62: gbp | I62: blo(spot) | M62: 2/1/2025 | N62: Monthly | Q62: 03321144 | R62: UK
B63: =RIGHT($C63,2) -> 84 | C63: ="c0"&RIGHT($D63,2) -> c084 | D63: o084 | E63: Canary Wharf (DS6) Limited | F63: uk | G63: n/a | H63: gbp | I63: blo(spot) | M63: 2/1/2025 | N63: Monthly | Q63: 03321660 | R63: UK
B64: =RIGHT($C64,2) -> 85 | C64: ="c0"&RIGHT($D64,2) -> c085 | D64: o085 | E64: Canary Wharf Holdings (DS6) Limited | F64: uk | G64: n/a | H64: gbp | I64: blo(spot) | M64: 2/1/2025 | N64: Monthly | Q64: 03321061 | R64: UK
... B66: =RIGHT($C66,2) -> 87 | C66: ="c0"&RIGHT($D66,2) -> c087 | D66: o087 | E66: CWCB Investments (DS6) Limited | F66: uk | G66: n/a | H66: gbp | I66: blo(spot) | M66: 2/1/2025 | N66: Monthly | Q66: 03941686 | R66: UK
B67: =RIGHT($C67,2) -> 88 | C67: ="c0"&RIGHT($D67,2) -> c088 | D67: o088 | E67: Canary Wharf Holdings Limited | F67: uk | G67: Invoice | H67: gbp | I67: blo(spot) | J67: sales | K67: purch | L67: 512639654 | M67: 2/1/2025 | N67: Monthly | O67: vgrp001 | P67: VAT Group - Canary Wharf Limited | Q67: 02798284 | R67: UK
B68: =RIGHT($C68,2) -> 90 | C68: ="c0"&RIGHT($D68,2) -> c090 | D68: o090 | E68: Canary Wharf Estate Limited | F68: uk | G68: Invoice | H68: gbp | I68: blo(spot) | J68: sales | K68: purch | L68: 512639654 | M68: 2/1/2025 | N68: Monthly | O68: vgrp001 | P68: VAT Group - Canary Wharf Limited | Q68: 03114622 | R68: UK
B69: =RIGHT($C69,2) -> 91 | C69: ="c0"&RIGHT($D69,2) -> c091 | D69: o091 | E69: Canary Wharf Group plc | F69: uk | G69: Invoice | H69: gbp | I69: blo(spot) | J69: sales | K69: purch | L69: 512639654 | M69: 2/1/2025 | N69: Monthly | O69: vgrp001 | P69: VAT Group - Canary Wharf Limited | Q69: 04191122 | R69: UK
B70: =RIGHT($C70,2) -> a2 | C70: ="c0"&RIGHT($D70,2) -> c0a2 | D70: o0a2 | E70: CLOSED - Canary Wharf Finance Limited | F70: uk | G70: n/a | H70: gbp | I70: blo(spot) | M70: 2/1/2025 | N70: Monthly | Q70: 03416151 | R70: UK
B71: =RIGHT($C71,2) -> a4 | C71: ="c0"&RIGHT($D71,2) -> c0a4 | D71: o0a4 | E71: CW Properties DS7B Limited | F71: uk | G71: n/a | H71: gbp | I71: blo(spot) | M71: 2/1/2025 | N71: Monthly | Q71: 03441686 | R71: UK
B72: =RIGHT($C72,2) -> a5 | C72: ="c0"&RIGHT($D72,2) -> c0a5 | D72: o0a5 | E72: CW Leasing DS7B Limited | F72: uk | G72: n/a | H72: gbp | I72: blo(spot) | M72: 2/1/2025 | N72: Monthly | Q72: 03441728 | R72: UK
B73: =RIGHT($C73,2) -> a7 | C73: ="c0"&RIGHT($D73,2) -> c0a7 | D73: o0a7 | E73: CW Properties DS7F Limited | F73: uk | G73: n/a | H73: gbp | I73: blo(spot) | M73: 2/1/2025 | N73: Monthly | Q73: 03441707 | R73: UK
B74: =RIGHT($C74,2) -> a8 | C74: ="c0"&RIGHT($D74,2) -> c0a8 | D74: o0a8 | E74: CW Leasing DS7F Limited | F74: uk | G74: n/a | H74: gbp | I74: blo(spot) | M74: 2/1/2025 | N74: Monthly | Q74: 03441740 | R74: UK
B75: =RIGHT($C75,2) -> ac | C75: ="c0"&RIGHT($D75,2) -> c0ac | D75: o0ac | E75: One Canada Square (Retail) Unit Trust | F75: uk | G75: n/a | H75: gbp | I75: blo(spot) | M75: 2/1/2025 | N75: Monthly | R75: JERSEY
B76: =RIGHT($C76,2) -> af | C76: ="c0"&RIGHT($D76,2) -> c0af | D76: o0af | E76: Canada Place (Retail) Unit Trust | F76: uk | G76: n/a | H76: gbp | I76: blo(spot) | M76: 2/1/2025 | N76: Monthly | R76: JERSEY
B77: =RIGHT($C77,2) -> ai | C77: ="c0"&RIGHT($D77,2) -> c0ai | D77: o0ai | E77: Cabot Place (Retail) Unit Trust | F77: uk | G77: n/a | H77: gbp | I77: blo(spot) | M77: 1/1/2025 | N77: Quarterly | R77: JERSEY
B78: =RIGHT($C78,2) -> al | C78: ="c0"&RIGHT($D78,2) -> c0al | D78: o0al | E78: Canada Place Mall (Retail) Unit Trust | F78: uk | G78: n/a | H78: gbp | I78: blo(spot) | M78: 2/1/2025 | N78: Monthly | R78: JERSEY
B79: =RIGHT($C79,2) -> ao | C79: ="c0"&RIGHT($D79,2) -> c0ao | D79: o0ao | E79: Jubilee Place (Retail) Unit Trust | F79: uk | G79: Invoice | H79: gbp | I79: blo(spot) | J79: sales | K79: purch | L79: 875212325 | M79: 2/1/2025 | N79: Quarterly | R79: JERSEY
B80: =RIGHT($C80,2) -> ar | C80: ="c0"&RIGHT($D80,2) -> c0ar | D80: o0ar | E80: 10 Cabot Square I Unit Trust | F80: uk | G80: n/a | H80: gbp | I80: blo(spot) | M80: 2/1/2025 | N80: Monthly | Q80: SL005918 | R80: JERSEY
B81: =RIGHT($C81,2) -> au | C81: ="c0"&RIGHT($D81,2) -> c0au | D81: o0au | E81: 10 Cabot Square II Unit Trust | F81: uk | G81: n/a | H81: gbp | I81: blo(spot) | M81: 2/1/2025 | N81: Monthly | Q81: 2732071 | R81: JERSEY
B82: =RIGHT($C82,2) -> ax | C82: ="c0"&RIGHT($D82,2) -> c0ax | D82: o0ax | E82: 20 Cabot Square I Unit Trust | F82: uk | G82: n/a | H82: gbp | I82: blo(spot) | M82: 2/1/2025 | N82: Monthly | R82: JERSEY
B83: =RIGHT($C83,2) -> b7 | C83: ="c0"&RIGHT($D83,2) -> c0b7 | D83: o0b7 | E83: CWCB Holdings Limited | F83: uk | G83: n/a | H83: gbp | I83: blo(spot) | M83: 2/1/2025 | N83: Monthly | Q83: 03452890 | R83: UK
B84: =RIGHT($C84,2) -> b8 | C84: ="c0"&RIGHT($D84,2) -> c0b8 | D84: o0b8 | E84: CWCB Investments (RT2) Limited | F84: uk | G84: Invoice | H84: gbp | I84: blo(spot) | J84: sales | K84: purch | L84: 872547301 | M84: 2/1/2025 | N84: Quarterly | Q84: 03452901 | R84: UK
B85: =RIGHT($C85,2) -> ba | C85: ="c0"&RIGHT($D85,2) -> c0ba | D85: o0ba | E85: 20 Cabot Square II Unit Trust | F85: uk | G85: n/a | H85: gbp | I85: blo(spot) | M85: 2/1/2025 | N85: Monthly | R85: JERSEY
B86: =RIGHT($C86,2) -> bd | C86: ="c0"&RIGHT($D86,2) -> c0bd | D86: o0bd | E86: CLOSED - Canary Wharf Finance III Limited | F86: uk | G86: n/a | H86: gbp | I86: blo(spot) | M86: 2/1/2025 | N86: Monthly | Q86: 05909641 | R86: UK
B87: =RIGHT($C87,2) -> bf | C87: ="c0"&RIGHT($D87,2) -> c0bf | D87: o0bf | E87: 10 Cabot Square I Unit Trust LP Limited | F87: uk | G87: n/a | H87: gbp | I87: blo(spot) | M87: 2/1/2025 | N87: Monthly | Q87: SC312220 | R87: SCOTTISH
B88: =RIGHT($C88,2) -> bg | C88: ="c0"&RIGHT($D88,2) -> c0bg | D88: o0bg | E88: 10 Cabot Square I Unit Trust GP Limited | F88: uk | G88: n/a | H88: gbp | I88: blo(spot) | M88: 2/1/2025 | N88: Monthly | Q88: SC312223 | R88: SCOTTISH
B89: =RIGHT($C89,2) -> bh | C89: ="c0"&RIGHT($D89,2) -> c0bh | D89: o0bh | E89: 10 Cabot Square I Unit Trust SLP | F89: uk | G89: n/a | H89: gbp | I89: blo(spot) | M89: 2/1/2025 | N89: Monthly | Q89: SL005918 | R89: SCOTTISH
B90: =RIGHT($C90,2) -> bj | C90: ="c0"&RIGHT($D90,2) -> c0bj | D90: o0bj | E90: 10 Cabot Square II Unit Trust LP Limited | F90: uk | G90: n/a | H90: gbp | I90: blo(spot) | M90: 2/1/2025 | N90: Monthly | Q90: SC312226 | R90: SCOTTISH
B91: =RIGHT($C91,2) -> bk | C91: ="c0"&RIGHT($D91,2) -> c0bk | D91: o0bk | E91: 10 Cabot Square II Unit Trust GP Limited | F91: uk | G91: n/a | H91: gbp | I91: blo(spot) | M91: 2/1/2025 | N91: Monthly | Q91: SC312216 | R91: SCOTTISH
B92: =RIGHT($C92,2) -> bl | C92: ="c0"&RIGHT($D92,2) -> c0bl | D92: o0bl | E92: 10 Cabot Square II Unit Trust SLP | F92: uk | G92: n/a | H92: gbp | I92: blo(spot) | M92: 2/1/2025 | N92: Monthly | Q92: SL005919 | R92: SCOTTISH
B93: =RIGHT($C93,2) -> bm | C93: ="c0"&RIGHT($D93,2) -> c0bm | D93: o0bm | E93: 20 Cabot Square I Unit Trust LP Limited | F93: uk | G93: n/a | H93: gbp | I93: blo(spot) | M93: 2/1/2025 | N93: Monthly | Q93: SC312214 | R93: SCOTTISH
B94: =RIGHT($C94,2) -> bn | C94: ="c0"&RIGHT($D94,2) -> c0bn | D94: o0bn | E94: 20 Cabot Square I Unit Trust GP Limited | F94: uk | G94: n/a | H94: gbp | I94: blo(spot) | M94: 2/1/2025 | N94: Monthly | Q94: SC312228 | R94: SCOTTISH
B95: =RIGHT($C95,2) -> bp | C95: ="c0"&RIGHT($D95,2) -> c0bp | D95: o0bp | E95: 20 Cabot Square I Unit Trust SLP | F95: uk | G95: n/a | H95: gbp | I95: blo(spot) | M95: 2/1/2025 | N95: Monthly | Q95: SL005920 | R95: SCOTTISH
B96: =RIGHT($C96,2) -> bq | C96: ="c0"&RIGHT($D96,2) -> c0bq | D96: o0bq | E96: 20 Cabot Square II Unit Trust LP Limited | F96: uk | G96: n/a | H96: gbp | I96: blo(spot) | M96: 2/1/2025 | N96: Monthly | Q96: SC312229 | R96: SCOTTISH
B97: =RIGHT($C97,2) -> br | C97: ="c0"&RIGHT($D97,2) -> c0br | D97: o0br | E97: 20 Cabot Square II Unit Trust GP Limited | F97: uk | G97: n/a | H97: gbp | I97: blo(spot) | M97: 2/1/2025 | N97: Monthly | Q97: SC312227 | R97: SCOTTISH
... B107: =RIGHT($C107,2) -> c2 | C107: ="c0"&RIGHT($D107,2) -> c0c2 | D107: o0c2 | E107: Canary Wharf Contractors (RT2) Limited | F107: uk | G107: n/a | H107: gbp | I107: blo(spot) | M107: 2/1/2025 | N107: Monthly | Q107: 03510961 | R107: UK
B108: =RIGHT($C108,2) -> c4 | C108: ="c0"&RIGHT($D108,2) -> c0c4 | D108: o0c4 | E108: Canary Wharf (Car Parks) Limited | F108: uk | G108: Invoice | H108: gbp | I108: blo(spot) | J108: sales | K108: purch | L108: 726741426 | M108: 12/1/2024 | N108: Quarterly | Q108: 03682170 | R108: UK
B109: =RIGHT($C109,2) -> c7 | C109: ="c0"&RIGHT($D109,2) -> c0c7 | D109: o0c7 | E109: Cabot Place (RT2) Limited | F109: uk | G109: Invoice | H109: gbp | I109: blo(spot) | J109: sales | K109: purch | L109: 744351734 | M109: 1/1/2025 | N109: Quarterly | Q109: 03719122 | R109: UK
B110: =RIGHT($C110,2) -> c8 | C110: ="c0"&RIGHT($D110,2) -> c0c8 | D110: o0c8 | E110: Canary Wharf (DS8) Limited | F110: uk | G110: n/a | H110: gbp | I110: blo(spot) | M110: 2/1/2025 | N110: Monthly | Q110: 03954236 | R110: UK
B111: =RIGHT($C111,2) -> c9 | C111: ="c0"&RIGHT($D111,2) -> c0c9 | D111: o0c9 | E111: Canary Wharf Holdings (DS8) Limited | F111: uk | G111: n/a | H111: gbp | I111: blo(spot) | M111: 2/1/2025 | N111: Monthly | Q111: 03957445 | R111: UK
B112: =RIGHT($C112,2) -> ca | C112: ="c0"&RIGHT($D112,2) -> c0ca | D112: o0ca | E112: Canada Place Mall (Retail) Unit Trust GP Limited | F112: uk | G112: n/a | H112: gbp | I112: blo(spot) | M112: 2/1/2025 | N112: Monthly | Q112: SC312207 | R112: SCOTTISH
B113: =RIGHT($C113,2) -> cb | C113: ="c0"&RIGHT($D113,2) -> c0cb | D113: o0cb | E113: Canada Place Mall (Retail) Unit Trust SLP | F113: uk | G113: n/a | H113: gbp | I113: blo(spot) | M113: 2/1/2025 | N113: Monthly | Q113: SL005916 | R113: SCOTTISH
...

Sheet Property Listing by LE
B3: Property Listing by Legal Entity as at 8 March 2025
B4: Legal Entity | C4: Property | D4: Property Name | E4: Property Address | F4: City | G4: County | H4: PostCode | I4: Units | J4: TAX Authority | K4: TAX Point | L4: Currency | M4: Rate Provider | N4: Primary Contact | O4: Phone | P4: E-mail | Q4: Contact Role | R4: Contact Company Name | S4: Contact Address | T4: Contact City | U4: County | V4: PostCode
B5: o001
B6: o001 | C6: c001 | D6: Canary Wharf Limited | J6: uk | K6: Invoice | L6: gbp | M6: blo(spot)
B7: o001 | C7: p112 | D7: Westferry Pier - Co. 01 | I7: 1120T020, 112OT010 | J7: uk | K7: Invoice | L7: gbp | M7: blo(spot)
B8: o001 | C8: p115 | D8: Cabot Square Watercourts Retail - Co. 01 (17303) | I8: 11500010, 11500020, 11500030, 115OS010, 115OS015, 115OS050, 115OTH10, 115OTH20, 115OTH30, 115OTH40, 115ST010 | J8: uk | K8: Invoice | L8: gbp | M8: blo(spot)
B9: o001 | C9: p141 | D9: 20 Colombus Court Yard - Co. 01 (B5 27001) | E9: 20 Columbus Courtyard | F9: London | H9: E14 4DA | I9: 14100010, 141OT010, 141P1010, 141P1020, 141P1030, 141P1095 | J9: uk | K9: Invoice | L9: gbp | M9: blo(spot)
B10: o001 | C10: p152 | D10: 8 Canada Square Office - Co. 01 (DS2 42001) | E10: 8 - 14 Canada Square | F10: London | H10: E14 5HQ | I10: 15200010, 152OT010 | J10: uk | K10: Invoice | L10: gbp | M10: blo(spot)
B11: o001 | C11: p155 | D11: 20 Canada Square Office - Co. 01 (DS4 44001) | E11: 20 Canada Square | F11: London | H11: E14 5NN | I11: 15500008, 15500010, 15500020, 15500030, 15500040, 15500050, 1550006A, 15500070, 15500100, 15501010, 15502010, 15503010, 15504010, 15505010, 15505020, 15505030, 15505040, 15506010, 15506020, 15507010, 15508010, 15509010, 15510010, 15511010, 15512010, 155B1010, 155B1020, 155ECC01, 155ECC02, 155ECC03, 155OT010, 155P1001, 155P1002, 155P1003, 155P1004, 155P1005, 155P1006, 155P1007, 155P1008, 155P1009, 155P1010, 155P1011, 155P1012, 155P1013, 155P1014, 155P1015, 155P1016, 155P1017, 155P1018, 155P1019, 155P1020, 155P1021, 155P1022, 155PR010, 155ST010, 155ST020, 155ST030, 155ST040, 155ST050, 155ST060, 155ST070, 155ST080, 155ST090, 155ST100, 155ST110 | J11: uk | K11: Invoice | L11: gbp | M11: blo(spot)
B12: o001 | C12: p163 | D12: 25 Churchill Place - Co. 01 (BP4 54001) | E12: 25 Churchill Place | F12: London | H12: E14 5RE | I12: 16301010, 16302010, 16303010, 16304010, 16305010, 16306010, 16307010, 16308010, 16309010, 16310010, 16311010, 16313010, 16314010, 16315010, 16316010, 16317010, 16318010, 16319010, 16320010, 16321010, 16322010, 163ENE10, 163GR010, 163GR020, 163PR010, 163ST010, 163ST020 | J12: uk | K12: Invoice | L12: gbp | M12: blo(spot)
B13: o001 | C13: p231 | D13: OLD - Reuters Plaza Kiosk - Co. 01 (Nash Court 16002) | E13: Reuters Plaza | F13: London | I13: 231000K1, 231000K2, 231000K3, 231000K4, 231000K5, 23100K2A, 231OS0K5, 231OTH10 | J13: uk | K13: Invoice | L13: gbp | M13: blo(spot)
B14: o001 | C14: p246 | D14: Kiosk 20 and Pontoon - Co. 01 (WW) | E14: 22 Churchill Place | F14: London | H14: E14 | I14: 24600010 | J14: uk | K14: Invoice | L14: gbp | M14: blo(spot) | Q14: Leasing Administration
B15: o001 | C15: p300 | D15: 8 Canada Square Retail - Co. 01 (DS2 42001) | E15: 8 - 14 Canada Square | F15: London | H15: E14 5HQ | J15: uk | K15: Invoice | L15: gbp | M15: blo(spot)
B16: o001 | C16: p301 | D16: 20 Canada Square Retail - Co. 01 (DS4 44001) | E16: 20 Canada Square | F16: London | H16: E14 5NN | J16: uk | K16: Invoice | L16: gbp | M16: blo(spot)
B17: o001 | C17: p346 | D17: Reuters Plaza Promenade - Co. 01 | I17: 346OS010 | J17: uk | K17: Invoice | L17: gbp | M17: blo(spot)
B19: o002
B20: o002 | C20: c002 | D20: Canary Wharf Contractors Limited | J20: uk | K20: Invoice | L20: gbp | M20: blo(spot)
B22: o003
B23: o003 | C23: c003 | D23: Heron Quays Properties Limited | J23: uk | K23: Invoice | L23: gbp | M23: blo(spot)
B24: o003 | C24: p132 | D24: OLD - East Wintergarden - Co. 03 (77201) | E24: 43 Bank Street, Heron Quay | F24: London | H24: E14 5NX | I24: 13200010, 13200020, 132OS010, 132OT010, 132ST010, 132ST020, 132ST030 | J24: uk | K24: Invoice | L24: gbp | M24: blo(spot)
B25: o003 | C25: p133 | D25: OLD - West Wintergarden - Co. 03 (77311) | E25: 35 Bank Street, Heron Quay | F25: London | H25: E14 5NW | I25: 13300010, 13300020, 13300030 | J25: uk | K25: Invoice | L25: gbp | M25: blo(spot)
B26: o003 | C26: p232 | D26: 40 Bank Street - Leasebacks - Co. 03 (HQ3 73001) | E26: 40 Bank Street | F26: London | H26: E14 5NR | I26: 23203010, 23205010, 23206010, 23207010, 232P1010 | J26: uk | K26: Invoice | L26: gbp | M26: blo(spot)
B28: o004 | Q28: Leasing Administration
B29: o004 | C29: c004 | D29: Canary Wharf Investments Limited | J29: uk | K29: Invoice | L29: gbp | M29: blo(spot)
B30: o004 | C30: p122 | D30: OLD - DS4 Link Retail - Co. 04 (44002) | I30: 122ST001, 122ST002, 122ST003, 122ST004, 122ST005 | J30: uk | K30: Invoice | L30: gbp | M30: blo(spot)
B31: o004 | C31: p123 | D31: INACTIVE: Jubilee Link East Retail - Co. 04 (19005) | I31: 123000K1 | J31: uk | K31: Invoice | L31: gbp | M31: blo(spot)
B32: o004 | C32: p125 | D32: OLD - 6 Chancellor Passage - Co. 04 (34006) | E32: 6 Chancellor Passage | F32: London | H32: E14 5EA | I32: 12500030, 12500040, 125OS010 | J32: uk | K32: Invoice | L32: gbp | M32: blo(spot)
B33: o004 | C33: p130 | D33: Montgomery Square - Co. 04 (77101) | E33: 1-10 Montgomery Square | F33: London | H33: E14 | I33: 13000001, 13000002, 130OTH01 | J33: uk | K33: Invoice | L33: gbp | M33: blo(spot)
B34: o004 | C34: p135 | D34: 1 Park Place - Co. 04 (81001) | E34: 1 Park Place | F34: London | H34: E14 | J34: uk | K34: Invoice | L34: gbp | M34: blo(spot)
B35: o004 | C35: p139 | D35: 11 Westferry Circus Office - Co. 04 (B3 25001) | E35: 11 Westferry Circus | F35: London | H35: E14 4HE | I35: 13900001, 139OT010, 139P1001 | J35: uk | K35: Invoice | L35: gbp | M35: blo(spot)
B36: o004 | C36: p153 | D36: 30 North Colonnade - Co. 04 (DS3E 43011) | E36: 30 North Colonnade | F36: London | H36: E14 5GN | I36: 15300001, 15301010, 15302010, 15303010, 15304010, 15305010, 15306010, 15307010, 15308010, 15309010, 15310010, 15311010, 15312010, 15313010, 15313020, 153ENE10, 153GR010, 153GR020, 153OT010, 153OT020, 153ST010, 153ST014, 153ST015, 153ST020, 153ST030, 153ST040 | J36: uk | K36: Invoice | L36: gbp | M36: blo(spot)
B37: o004 | C37: p154 | D37: 15 Canada Square - Co. 04 (DS3W 43021) | E37: 15 Canada Square | F37: London | H37: E14 5EQ | I37: 15401010, 15402010, 15403010, 15404010, 15405010, 15406010, 15407010, 15408010, 15409010, 15410010, 15411010, 15412010, 15413010, 15414010, 154GR010, 154GR020, 154OT010, 154ST020, 154ST030, 154ST040, 158OT020 | J37: uk | K37: Invoice | L37: gbp | M37: blo(spot)
B38: o004 | C38: p162 | D38: 20 Churchill Place - Co. 04 (BP3 53001) | E38: 20 Churchill Place | F38: London | H38: E14 5HJ | I38: 16201010, 16202010, 16203010, 16204010, 16205010, 16206010, 16207010, 16208010, 16209010, 16210010, 16211010, 16212010, 162B1010, 162ENE10, 162GR010, 162OT010, 162OT020, 162PR010 | J38: uk | K38: Invoice | L38: gbp | M38: blo(spot)
B39: o004 | C39: p187 | D39: Suite 1 Beatty House, Admirals Way - Co. 04 (81101) | E39: Suite 1, Beatty House Admirals Way | F39: London | H39: E14 9UD | J39: uk | K39: Invoice | L39: gbp | M39: blo(spot)
B40: o004 | C40: p188 | D40: Suite 3 Cochrane House, Admirals Way - Co. 04 (81201) | E40: Suite 3, Cochrane House Admirals Way | F40: London | H40: E14 9UD | J40: uk | K40: Invoice | L40: gbp | M40: blo(spot)
B41: o004 | C41: p189 | D41: Suite 3 Parker House, Admirals Way - Co. 04 (81503) | E41: Suite 3, Parker House Admirals Way | F41: London | H41: E14 9UQ | J41: uk | K41: Invoice | L41: gbp | M41: blo(spot)
B42: o004 | C42: p190 | D42: Suite 4 Parker House, Admirals Way - Co. 04 (81504) | E42: Suite 4, Parker House Admirals Way | F42: London | H42: E14 9UQ | J42: uk | K42: Invoice | L42: gbp | M42: blo(spot)
B43: o004 | C43: p191 | D43: Suite 4 Raleigh House, Admirals Way - Co. 04 (81604) | E43: Suite 4, Raleigh House Admirals Way | F43: London | H43: E14 9SN | J43: uk | K43: Invoice | L43: gbp | M43: blo(spot)
B44: o004 | C44: p192 | D44: Suite 39 Beaufort Court, Admirals Way - Co. 04 (81739) | E44: Suite 39, Beaufort Court Admirals Way | F44: London | H44: E14 9XL | J44: uk | K44: Invoice | L44: gbp | M44: blo(spot)
B45: o004 | C45: p233 | D45: Churchill Place Prayer & Consultation Room, Units A & B - Co. 04 (RT4 55001) | E45: 2 Churchill Place | F45: London | H45: E14 5HU | I45: 233000A1, 233000B1, 23300CON, 23300PRA, 233P1001 | J45: uk | K45: Invoice | L45: gbp | M45: blo(spot)
B46: o004 | C46: p234 | D46: Churchill Place Bicycle Storage - Co. 04 (15308) | E46: Churchill Place Car Park | F46: London | H46: E14 5HP | J46: uk | K46: Invoice | L46: gbp | M46: blo(spot)
B47: o004 | C47: p274 | D47: OLD - 5 Frobisher Passage - Co. 04 | E47: 5 Frobisher Passage | H47: E14 4EE | I47: 27400010, 274OS010 | J47: uk | K47: Invoice | L47: gbp | M47: blo(spot)
B48: o004 | C48: p275 | D48: OLD - 6 Frobisher Passage - Co. 04 | E48: 6 Frobisher Passage | F48: London | H48: E14 4EE | I48: 27500010, 27500020, 27500030, 27500040, 275OS010 | J48: uk | K48: Invoice | L48: gbp | M48: blo(spot) | Q48: Leasing Administration
B49: o004 | C49: p284 | D49: INACTIVE: 20 Canada Square Grd Rent - Co. 04 (DS4 44001) | E49: 20 Canada Square | F49: London | H49: E14 5NN | I49: 15500008, 15500010, 15500020, 15500030, 15500040, 15500050, 1550006A, 15500070, 15500100, 15501010, 15502010, 15503010, 15504010, 15505010, 15505020, 15505030, 15505040, 15507010, 15508010, 15509010, 15510010, 15511010, 15512010, 155ECC01, 155ECC02, 155ECC03, 155OT010, 155P1001, 155P1002, 155P1003, 155P1004, 155P1005, 155P1006, 155P1007, 155P1008, 155P1009, 155P1010, 155P1011, 155P1012, 155P1013, 155P1014, 155P1015, 155P1016, 155P1017, 155P1018, 155P1019, 155P1020, 155P1021, 155P1022, 155PR010, 155ST010, 155ST020, 155ST030, 155ST040, 155ST050, 155ST060, 155ST070, 155ST080, 155ST090, 155ST100, 155ST110, 284OT010 | J49: uk | K49: Invoice | L49: gbp | M49: blo(spot)
B50: o004 | C50: p298 | D50: 11 Westferry Circus Retail - Co. 04 (B3 25001) | E50: 11 Westferry Circus | F50: London | H50: E14 4HE | J50: uk | K50: Invoice | L50: gbp | M50: blo(spot)
B51: o004 | C51: p341 | D51: 25 Churchill Place Dock Level - Co. 04 | E51: 25 Churchill Place | F51: London | H51: E14 | I51: 341OS010 | J51: uk | K51: Invoice | L51: gbp | M51: blo(spot)
B52: o004 | C52: p344 | D52: 20 Canada Square Grd Rent - Co. 04 (DS4 44001) | E52: 20 Canada Square | F52: London | H52: E14 5NN | I52: 15500008, 15500010, 15500020, 15500030, 15500040, 15500050, 1550006A, 15500070, 15500100, 15501010, 15502010, 15503010, 15504010, 15505010, 15505020, 15505030, 15505040, 15507010, 15508010, 15509010, 15510010, 15511010, 15512010, 155ECC01, 155ECC02, 155ECC03, 155OT010, 155P1001, 155P1002, 155P1003, 155P1004, 155P1005, 155P1006, 155P1007, 155P1008, 155P1009, 155P1010, 155P1011, 155P1012, 155P1013, 155P1014, 155P1015, 155P1016, 155P1017, 155P1018, 155P1019, 155P1020, 155P1021, 155P1022, 155PR010, 155ST010, 155ST020, 155ST030, 155ST040, 155ST050, 155ST060, 155ST070, 155ST080, 155ST090, 155ST100, 155ST110, 284OT010 | J52: uk | K52: Invoice | L52: gbp | M52: blo(spot)
B53: o004 | C53: p345 | D53: Jubilee Link East Retail - Co. 04 (19005) | I53: 123000K1 | J53: uk | K53: Invoice | L53: gbp | M53: blo(spot)
B55: o005
B56: o005 | C56: c005 | D56: Cabot Place Limited | J56: uk | K56: Invoice | L56: gbp | M56: blo(spot)
B57: o005 | C57: p116 | D57: OLD - Cabot Place Retail - Co. 05 (RT1 17002) | E57: 15 Cabot Square | F57: London | H57: E14 4QT | I57: 11600001, 11600002, 11600003, 11600004, 11600005, 11600006, 11600007, 11600008, 1160000A, 1160000B, 11600010, 11600012, 11600013, 11600019, 1160004A, 1160004B, 1160008A, 11600100, 1160010A, 11600200, 11600210, 11600214, 11600220, 11600230, 11600250, 11600255, 11600260, 11600270, 11600300, 11600330, 11600365, 11600380, 11600390, 11600398, 11600400, 11601101, 11601102, 11601214, 11601301, 11601305, 11601310, 11601315, 11601320, 11601330, 11601331, 11601340, 11601355, 11601360, 11602100, 11602150, 11602200, 11602210, 11602250, 11602300, 11602350, 11602400, 116ATM01, 116ENE10, 116GR009, 116GR130, 116GR145, 116GR150, 116GR155, 116GR160, 116GR165, 116GR190, 116GR311, 116GR315, 116GR320, 116GR330, 116GR335, 116GR340, 116GR350, 116GR360, 116GR370, 116IPT10, 116M1ERO, 116M1ERR, 116OS010, 116OS020, 116OS030, 116OS040, 116OTH01, 116P1002, 116ST001, 116ST004, 116ST005, 116ST00A, 116ST00B, 116ST00C, 116ST00D, 116ST00E, 116ST00F, 116ST00G, 116ST00H, 116ST00I, 116ST00J, 116ST00N, 116ST010, 116ST01B, 116ST020, 116ST02A, 116ST02B, 116ST035, 116ST03A, 116ST040, 116ST050, 116ST060, 116ST0LB, 116ST100, 116ST101, 116ST10B, 116ST16A, 116ST1P2, 116ST201, 116ST202, 116ST203, 116ST204, 116ST206, 116ST207, 116ST217, 116ST22A, 116ST23B, 116ST23C, 116ST23D, 116ST25A, 116ST270, 116ST2P2, 116ST301, 116ST305, 116ST306, 116ST307, 116ST308, 116ST310, 116ST311, 116ST312, 116ST31B, 116ST320, 116ST33A, 116ST33B, 116ST34A, 116ST34B, 116ST370, 116ST401, 116ST402, 116ST403, 116ST404, 116ST405, 116ST406, 116ST407, 116ST408, 116ST409, 116ST411, 116ST412, 116ST413, 116ST414, 116ST415, 116ST416, 116ST418, 116ST419, 116ST41A, 116ST41B, 116ST420, 116ST421, 116ST422, 116ST470 | J57: uk | K57: Invoice | L57: gbp | M57: blo(spot)
B58: o005 | C58: p159 | D58: OLD - One Canada Square Retail - Co. 05 (DS7 Retail 47002) | E58: One Canada Square (Concourse) | F58: London | H58: E14 5AX | I58: 129OS020, 15900001, 15900002, 15900040, 15900050, 15900410, 15900420, 15900430, 15900431, 15900440, 15900443, 15900445, 15900450, 15900452, 15900456, 15900457, 15900462, 15900463, 15900464, 15900470, 15900472, 15900475, 15900480, 15900485, 15900490, 15900491, 15900600, 15900652, 159OS010, 159ST020, 159ST040, 159ST050, 159ST452, 159ST457 | J58: uk | K58: Invoice | L58: gbp | M58: blo(spot)
B60: o006
B61: o006 | C61: c006 | D61: Canary Wharf Management Limited | J61: uk | K61: Invoice | L61: gbp | M61: blo(spot)
B62: o006 | C62: e101 | D62: Estate - Co. 06 | J62: uk | K62: Invoice | L62: gbp | M62: blo(spot)
B63: o006 | C63: p101 | D63: Estate - Co. 06 | I63: 10100010, 10100020, 10100030, 10100040, 10100050, 10100060 | J63: uk | K63: Invoice | L63: gbp | M63: blo(spot)
B64: o006 | C64: p110 | D64: Promotion Fund - Co. 06 (17101) | I64: 11000010, 11000020, 11000030, 11000040, 11000050, 11000060, 11000070, 11000080, 11000090, 11000100, 11000110, 11000120, 11000130 | J64: uk | K64: Invoice | L64: gbp | M64: blo(spot)
B65: o006 | C65: p124 | D65: OLD - 5 Chancellor Passage - Co. 06 (34005) | E65: 5 Chancellor Passage | F65: London | H65: E14 4PA | I65: 12400010, 124OS010 | J65: uk | K65: Invoice | L65: gbp | M65: blo(spot)
B66: o006 | C66: p142 | D66: 1 Cabot Square - Co. 06 (FC1 31001) | E66: 1 Cabot Square | F66: London | H66: E14 4QF | I66: 14200010, 142OT010 | J66: uk | K66: Invoice | L66: gbp | M66: blo(spot)
B67: o006 | C67: p148 | D67: 25 Cabot Square - Co. 06 (FC5 35001) | E67: 25 Cabot Square | F67: London | H67: E14 | I67: 14800010 | J67: uk | K67: Invoice | L67: gbp | M67: blo(spot)
B68: o006 | C68: p239 | D68: East Winter Garden CWML - Co. 06 | E68: 43 Bank Street Heron Quay | F68: London | H68: E14 5NX | J68: uk | K68: Invoice | L68: gbp | M68: blo(spot)
B69: o006 | C69: p240 | D69: Tenant Services CWML - Co. 06 | J69: uk | K69: Invoice | L69: gbp | M69: blo(spot)
B70: o006 | C70: p315 | D70: Waste Management - Co. 06 | E70: One Canada Square Canary Wharf | F70: London | H70: E145AB | J70: uk | K70: Invoice | L70: gbp | M70: blo(spot)
B71: o006 | C71: s103 | D71: Westferry Circus Car Park - Co. 06 (15108) | E71: Westferry Circus Car Park | F71: London | H71: E14 4HD | J71: uk | K71: Invoice | L71: gbp | M71: blo(spot) | Q71: Level 3 CW Facilities Management
B72: o006 | C72: s105 | D72: Churchill Place Car Park - Co. 06 (15308) | E72: Churchill Place Car Park | F72: London | H72: E14 5HP | J72: uk | K72: Invoice | L72: gbp | M72: blo(spot)
B73: o006 | C73: s107 | D73: Columbus Car Park - Co. 06 (15708) | J73: uk | K73: Invoice | L73: gbp | M73: blo(spot)
B74: o006 | C74: s113 | D74: Reuters Plaza Retail - Co. 06 (Nash Court 16002) | J74: uk | K74: Invoice | L74: gbp | M74: blo(spot)
B75: o006 | C75: s115 | D75: Cabot Square Watercourts Retail - Co. 06 (17303) | J75: uk | K75: Invoice | L75: gbp | M75: blo(spot) | Q75: Level 3 Car Parks - Columbus
B76: o006 | C76: s119 | D76: Churchill Place Retail - Co. 06 (RT4 55001) | J76: uk | K76: Invoice | L76: gbp | M76: blo(spot)
B77: o006 | C77: s120 | D77: Crossrail Retail - Co. 06 (RT5 60011) | J77: uk | K77: Invoice | L77: gbp | M77: blo(spot)
B78: o006 | C78: s121 | D78: DS3 Link Retail - Co. 06 (66001) | J78: uk | K78: Invoice | L78: gbp | M78: blo(spot) | Q78: Level 3 Retail - Churchill Place
B79: o006 | C79: s124 | D79: 5 Chancellor Passage - Co. 06 (34005) | J79: uk | K79: Invoice | L79: gbp | M79: blo(spot)
B80: o006 | C80: s125 | D80: 6 Chancellor Passage - Co. 06 (34006) | E80: c/o One Canada Square Canary Wharf | F80: London | H80: E14 5AB | J80: uk | K80: Invoice | L80: gbp | M80: blo(spot)
B81: o006 | C81: s126 | D81: Canada Square Park Pavilion - The Ivy - Co. 06 (49011) | J81: uk | K81: Invoice | L81: gbp | M81: blo(spot)
B82: o006 | C82: s127 | D82: Canada Square Pavilion - Co. 06 (DS7 Pav 47003, 49001) | J82: uk | K82: Invoice | L82: gbp | M82: blo(spot) | Q82: Level 3 Estate Retail
B83: o006 | C83: s129 | D83: Middle Dock, Building One - Co. 06 (98103) | J83: uk | K83: Invoice | L83: gbp | M83: blo(spot)
B84: o006 | C84: s131 | D84: Montgomery Square Marketing Suite - Co. 06 (77500) | J84: uk | K84: Invoice | L84: gbp | M84: blo(spot)
B85: o006 | C85: s132 | D85: East Wintergarden - Co. 06 | E85: 43 Bank Street, Heron Quay | F85: London | H85: E14 5NX | J85: uk | K85: Invoice | L85: gbp | M85: blo(spot) | Q85: Level 3 Estate Retail
B86: o006 | C86: s133 | D86: West Wintergarden - Co. 06 (77311) | J86: uk | K86: Invoice | L86: gbp | M86: blo(spot)
B87: o006 | C87: s134 | D87: Riverside - Co. 06 (28001, 29001) | J87: uk | K87: Invoice | L87: gbp | M87: blo(spot)
B88: o006 | C88: s136 | D88: 1 Westferry Circus - Co. 06 (B1 23001) | J88: uk | K88: Invoice | L88: gbp | M88: blo(spot)
B89: o006 | C89: s137 | D89: 7 Westferry Circus - Co. 06 (B2 24001) | J89: uk | K89: Invoice | L89: gbp | M89: blo(spot)
B90: o006 | C90: s138 | D90: 7 Westferry Circus Retail - Co. 06 (B2 Retail 24001) | J90: uk | K90: Invoice | L90: gbp | M90: blo(spot)
B91: o006 | C91: s139 | D91: 11 Westferry Circus - Co. 06 (B3 25001) | J91: uk | K91: Invoice | L91: gbp | M91: blo(spot)
B92: o006 | C92: s140 | D92: 17 Colombus Court Yard - Co. 06 (B4 26001) | J92: uk | K92: Invoice | L92: gbp | M92: blo(spot)
B93: o006 | C93: s141 | D93: 20 Colombus Court Yard - Co. 06 (B5 27001) | J93: uk | K93: Invoice | L93: gbp | M93: blo(spot)
B94: o006 | C94: s142 | D94: 1 Cabot Square - Co. 06 (FC1 31001) | J94: uk | K94: Invoice | L94: gbp | M94: blo(spot)
B95: o006 | C95: s143 | D95: 10 Cabot Square / 5 North Colonnade - Co. 06 (FC2 32001) | J95: uk | K95: Invoice | L95: gbp | M95: blo(spot)
B96: o006 | C96: s144 | D96: 10 Cabot Square Retail - Co. 06 (FC2 Retail 32002) | J96: uk | K96: Invoice | L96: gbp | M96: blo(spot)
B97: o006 | C97: s145 | D97: 25 North Colonnade - Co. 06 (FC3 33001) | J97: uk | K97: Invoice | L97: gbp | M97: blo(spot) | Q97: Level 3 1-5 Bank Street
B98: o006 | C98: s146 | D98: 20 Cabot Square / 10 South Colonnade - Co. 06 (FC4 34001) | J98: uk | K98: Invoice | L98: gbp | M98: blo(spot)
B99: o006 | C99: s147 | D99: 20 Cabot Square Retail - Co. 06 (FC4 Retail 34002) | J99: uk | K99: Invoice | L99: gbp | M99: blo(spot)
B100: o006 | C100: s148 | D100: 25 Cabot Square - Co. 06 (FC5 35001) | J100: uk | K100: Invoice | L100: gbp | M100: blo(spot)
B101: o006 | C101: s149 | D101: 30 South Colonnade - Co. 06 (FC6 36001) | J101: uk | K101: Invoice | L101: gbp | M101: blo(spot)
B102: o006 | C102: s150 | D102: 30 South Colonnade Retail - Co. 06 (FC6 Retail 36001) | J102: uk | K102: Invoice | L102: gbp | M102: blo(spot)
B103: o006 | C103: s151 | D103: 5 Canada Square - Co. 06 (DS1 41001) | J103: uk | K103: Invoice | L103: gbp | M103: blo(spot)
B104: o006 | C104: s152 | D104: 8 Canada Square - Co. 06 (DS2 42001) | J104: uk | K104: Invoice | L104: gbp | M104: blo(spot)
B105: o006 | C105: s153 | D105: 30 North Colonnade - Co. 06 (DS3E 43011) | J105: uk | K105: Invoice | L105: gbp | M105: blo(spot)
B106: o006 | C106: s154 | D106: 15 Canada Square - Co. 06 (DS3W 43021) | J106: uk | K106: Invoice | L106: gbp | M106: blo(spot)
B107: o006 | C107: s155 | D107: 20 Canada Square - Co. 06 (DS4 44001) | J107: uk | K107: Invoice | L107: gbp | M107: blo(spot)
...
